{"meta":{"country":"US","date":"2026-07-22","updatedAt":"2026-07-22 08:07:31 KST","status":"COMPLETED","totalTickers":6729,"detectedCombos":116,"source":"yahoo"},"results":[{"code":"LBGJ","name":"LBGJ","market":"US","currentPrice":0.0599,"currentChangePct":-73.02,"yearLow":0.0529,"yearHigh":177.0,"marketCap":null,"consecutiveDays":2,"totalChangePct":-97.51,"direction":"DOWN"},{"code":"GVH","name":"GVH","market":"US","currentPrice":1.1,"currentChangePct":-25.68,"yearLow":0.87,"yearHigh":10.74,"marketCap":null,"consecutiveDays":2,"totalChangePct":-76.89,"direction":"DOWN"},{"code":"PSNYW","name":"PSNYW","market":"US","currentPrice":2.86,"currentChangePct":-19.21,"yearLow":2.1,"yearHigh":14.4,"marketCap":null,"consecutiveDays":2,"totalChangePct":-45.52,"direction":"DOWN"},{"code":"HQWWW","name":"HQWWW","market":"US","currentPrice":6.0,"currentChangePct":-31.03,"yearLow":1.53,"yearHigh":33.0,"marketCap":null,"consecutiveDays":2,"totalChangePct":-45.5,"direction":"DOWN"},{"code":"CDTG","name":"CDTG","market":"US","currentPrice":1.01,"currentChangePct":-18.55,"yearLow":0.73,"yearHigh":53.25,"marketCap":null,"consecutiveDays":2,"totalChangePct":-43.58,"direction":"DOWN"},{"code":"GORO","name":"GORO","market":"US","currentPrice":2.58,"currentChangePct":-21.58,"yearLow":0.43,"yearHigh":4.0,"marketCap":null,"consecutiveDays":2,"totalChangePct":-39.29,"direction":"DOWN"},{"code":"VBIO","name":"VBIO","market":"US","currentPrice":0.311,"currentChangePct":-13.85,"yearLow":0.3102,"yearHigh":5.6,"marketCap":null,"consecutiveDays":2,"totalChangePct":-38.42,"direction":"DOWN"},{"code":"LSTA","name":"LSTA","market":"US","currentPrice":2.24,"currentChangePct":-36.54,"yearLow":1.81,"yearHigh":5.07,"marketCap":null,"consecutiveDays":2,"totalChangePct":-37.78,"direction":"DOWN"},{"code":"DARE","name":"DARE","market":"US","currentPrice":1.25,"currentChangePct":-6.72,"yearLow":1.23,"yearHigh":3.78,"marketCap":null,"consecutiveDays":2,"totalChangePct":-36.22,"direction":"DOWN"},{"code":"VEEE","name":"VEEE","market":"US","currentPrice":26.25,"currentChangePct":-10.99,"yearLow":4.16,"yearHigh":128.02,"marketCap":null,"consecutiveDays":2,"totalChangePct":-32.17,"direction":"DOWN"},{"code":"PYPD","name":"PYPD","market":"US","currentPrice":3.74,"currentChangePct":-27.38,"yearLow":3.06,"yearHigh":5.73,"marketCap":null,"consecutiveDays":2,"totalChangePct":-30.35,"direction":"DOWN"},{"code":"WCT","name":"WCT","market":"US","currentPrice":0.815,"currentChangePct":-23.8,"yearLow":0.815,"yearHigh":25.0,"marketCap":null,"consecutiveDays":2,"totalChangePct":-29.72,"direction":"DOWN"},{"code":"SLND","name":"SLND","market":"US","currentPrice":0.802,"currentChangePct":-22.85,"yearLow":0.62,"yearHigh":5.34,"marketCap":null,"consecutiveDays":2,"totalChangePct":-29.61,"direction":"DOWN"},{"code":"BIVI","name":"BIVI","market":"US","currentPrice":1.29,"currentChangePct":-9.47,"yearLow":1.06,"yearHigh":8.399,"marketCap":null,"consecutiveDays":2,"totalChangePct":-28.33,"direction":"DOWN"},{"code":"NTCL","name":"NTCL","market":"US","currentPrice":3.21,"currentChangePct":-18.53,"yearLow":3.11,"yearHigh":155.0,"marketCap":null,"consecutiveDays":2,"totalChangePct":-28.19,"direction":"DOWN"},{"code":"BIYA","name":"BIYA","market":"US","currentPrice":3.09,"currentChangePct":-11.97,"yearLow":2.75,"yearHigh":224.75,"marketCap":null,"consecutiveDays":2,"totalChangePct":-25.36,"direction":"DOWN"},{"code":"HQ","name":"HQ","market":"US","currentPrice":16.69,"currentChangePct":-14.85,"yearLow":8.29,"yearHigh":45.0,"marketCap":null,"consecutiveDays":2,"totalChangePct":-25.19,"direction":"DOWN"},{"code":"NVNI","name":"NVNI","market":"US","currentPrice":1.21,"currentChangePct":-8.33,"yearLow":0.769,"yearHigh":16.4,"marketCap":null,"consecutiveDays":2,"totalChangePct":-23.42,"direction":"DOWN"},{"code":"HCAI","name":"HCAI","market":"US","currentPrice":5.4,"currentChangePct":-9.4,"yearLow":3.96,"yearHigh":28.8,"marketCap":null,"consecutiveDays":2,"totalChangePct":-22.53,"direction":"DOWN"},{"code":"ATER","name":"ATER","market":"US","currentPrice":1.03,"currentChangePct":-17.6,"yearLow":0.515,"yearHigh":1.87,"marketCap":null,"consecutiveDays":2,"totalChangePct":-20.77,"direction":"DOWN"},{"code":"TOP","name":"TOP","market":"US","currentPrice":2.23,"currentChangePct":-0.45,"yearLow":0.612,"yearHigh":3.33,"marketCap":null,"consecutiveDays":2,"totalChangePct":-20.64,"direction":"DOWN"},{"code":"QH","name":"QH","market":"US","currentPrice":5.53,"currentChangePct":-3.66,"yearLow":0.017,"yearHigh":158.4,"marketCap":null,"consecutiveDays":2,"totalChangePct":-20.43,"direction":"DOWN"},{"code":"BJDX","name":"BJDX","market":"US","currentPrice":1.16,"currentChangePct":-4.13,"yearLow":1.03,"yearHigh":16.68,"marketCap":null,"consecutiveDays":2,"totalChangePct":-20.0,"direction":"DOWN"},{"code":"RITR","name":"RITR","market":"US","currentPrice":0.1536,"currentChangePct":-5.77,"yearLow":0.1525,"yearHigh":7.68,"marketCap":null,"consecutiveDays":2,"totalChangePct":-19.16,"direction":"DOWN"},{"code":"CNF","name":"CNF","market":"US","currentPrice":2.365,"currentChangePct":-7.98,"yearLow":2.2,"yearHigh":8.8,"marketCap":null,"consecutiveDays":2,"totalChangePct":-19.01,"direction":"DOWN"},{"code":"NEXR","name":"NEXR","market":"US","currentPrice":0.378,"currentChangePct":-2.27,"yearLow":0.36,"yearHigh":108.5,"marketCap":null,"consecutiveDays":2,"totalChangePct":-19.01,"direction":"DOWN"},{"code":"NIXX","name":"NIXX","market":"US","currentPrice":0.932,"currentChangePct":-12.9,"yearLow":0.474,"yearHigh":2.1,"marketCap":null,"consecutiveDays":2,"totalChangePct":-18.96,"direction":"DOWN"},{"code":"VFSWW","name":"VFSWW","market":"US","currentPrice":0.28,"currentChangePct":-8.46,"yearLow":0.11,"yearHigh":0.58,"marketCap":null,"consecutiveDays":2,"totalChangePct":-18.1,"direction":"DOWN"},{"code":"LGPS","name":"LGPS","market":"US","currentPrice":1.14,"currentChangePct":-8.8,"yearLow":0.45,"yearHigh":1.5,"marketCap":null,"consecutiveDays":2,"totalChangePct":-17.39,"direction":"DOWN"},{"code":"GOAI","name":"GOAI","market":"US","currentPrice":2.03,"currentChangePct":-13.98,"yearLow":1.69,"yearHigh":18.0,"marketCap":null,"consecutiveDays":2,"totalChangePct":-17.14,"direction":"DOWN"},{"code":"JLHL","name":"JLHL","market":"US","currentPrice":7.76,"currentChangePct":-9.87,"yearLow":2.7,"yearHigh":57.95,"marketCap":null,"consecutiveDays":2,"totalChangePct":-17.01,"direction":"DOWN"},{"code":"LEDS","name":"LEDS","market":"US","currentPrice":2.51,"currentChangePct":-8.73,"yearLow":1.01,"yearHigh":3.62,"marketCap":null,"consecutiveDays":2,"totalChangePct":-16.61,"direction":"DOWN"},{"code":"ADGM","name":"ADGM","market":"US","currentPrice":0.442,"currentChangePct":-13.33,"yearLow":0.4415,"yearHigh":2.582,"marketCap":null,"consecutiveDays":2,"totalChangePct":-16.6,"direction":"DOWN"},{"code":"BNZI","name":"BNZI","market":"US","currentPrice":2.02,"currentChangePct":-6.91,"yearLow":2.0,"yearHigh":88.7,"marketCap":null,"consecutiveDays":2,"totalChangePct":-16.53,"direction":"DOWN"},{"code":"CLDI","name":"CLDI","market":"US","currentPrice":0.0995,"currentChangePct":-14.22,"yearLow":0.097,"yearHigh":10.92,"marketCap":null,"consecutiveDays":2,"totalChangePct":-16.39,"direction":"DOWN"},{"code":"HPAI","name":"HPAI","market":"US","currentPrice":0.4501,"currentChangePct":-1.08,"yearLow":0.4201,"yearHigh":5.2,"marketCap":null,"consecutiveDays":2,"totalChangePct":-16.34,"direction":"DOWN"},{"code":"EVGN","name":"EVGN","market":"US","currentPrice":0.5321,"currentChangePct":-3.25,"yearLow":0.37,"yearHigh":1.5,"marketCap":null,"consecutiveDays":2,"totalChangePct":-15.54,"direction":"DOWN"},{"code":"FEDU","name":"FEDU","market":"US","currentPrice":8.49,"currentChangePct":-12.38,"yearLow":6.68,"yearHigh":17.3,"marketCap":null,"consecutiveDays":2,"totalChangePct":-15.4,"direction":"DOWN"},{"code":"LICN","name":"LICN","market":"US","currentPrice":1.15,"currentChangePct":-10.16,"yearLow":0.75,"yearHigh":9.494,"marketCap":null,"consecutiveDays":2,"totalChangePct":-14.81,"direction":"DOWN"},{"code":"ALTO","name":"ALTO","market":"US","currentPrice":4.98,"currentChangePct":-9.62,"yearLow":0.92,"yearHigh":6.11,"marketCap":null,"consecutiveDays":2,"totalChangePct":-14.73,"direction":"DOWN"},{"code":"GRAN","name":"GRAN","market":"US","currentPrice":1.52,"currentChangePct":-6.75,"yearLow":0.8,"yearHigh":5.91,"marketCap":null,"consecutiveDays":2,"totalChangePct":-14.61,"direction":"DOWN"},{"code":"TENB","name":"TENB","market":"US","currentPrice":34.09,"currentChangePct":-9.72,"yearLow":15.73,"yearHigh":43.67,"marketCap":null,"consecutiveDays":2,"totalChangePct":-14.52,"direction":"DOWN"},{"code":"VHUB","name":"VHUB","market":"US","currentPrice":0.893,"currentChangePct":-9.78,"yearLow":0.53,"yearHigh":40.3,"marketCap":null,"consecutiveDays":2,"totalChangePct":-14.12,"direction":"DOWN"},{"code":"UZX","name":"UZX","market":"US","currentPrice":0.232,"currentChangePct":-6.45,"yearLow":0.19,"yearHigh":3.1,"marketCap":null,"consecutiveDays":2,"totalChangePct":-13.75,"direction":"DOWN"},{"code":"LIDRW","name":"LIDRW","market":"US","currentPrice":0.019,"currentChangePct":-5.0,"yearLow":0.008,"yearHigh":0.58,"marketCap":null,"consecutiveDays":2,"totalChangePct":-13.64,"direction":"DOWN"},{"code":"ALIT","name":"ALIT","market":"US","currentPrice":18.78,"currentChangePct":-7.71,"yearLow":9.58,"yearHigh":116.0,"marketCap":null,"consecutiveDays":2,"totalChangePct":-13.62,"direction":"DOWN"},{"code":"INLF","name":"INLF","market":"US","currentPrice":2.23,"currentChangePct":-3.04,"yearLow":2.12,"yearHigh":4598.4,"marketCap":null,"consecutiveDays":2,"totalChangePct":-13.57,"direction":"DOWN"},{"code":"RPD","name":"RPD","market":"US","currentPrice":10.61,"currentChangePct":-11.21,"yearLow":4.97,"yearHigh":23.26,"marketCap":null,"consecutiveDays":2,"totalChangePct":-13.03,"direction":"DOWN"},{"code":"JSPR","name":"JSPR","market":"US","currentPrice":0.77,"currentChangePct":-5.41,"yearLow":0.315,"yearHigh":3.31,"marketCap":null,"consecutiveDays":2,"totalChangePct":-12.99,"direction":"DOWN"},{"code":"LEXX","name":"LEXX","market":"US","currentPrice":0.554,"currentChangePct":-7.7,"yearLow":0.46,"yearHigh":1.55,"marketCap":null,"consecutiveDays":2,"totalChangePct":-12.92,"direction":"DOWN"},{"code":"UPLD","name":"UPLD","market":"US","currentPrice":4.69,"currentChangePct":-4.87,"yearLow":4.0,"yearHigh":39.1,"marketCap":null,"consecutiveDays":2,"totalChangePct":-12.83,"direction":"DOWN"},{"code":"SPRO","name":"SPRO","market":"US","currentPrice":1.38,"currentChangePct":-4.17,"yearLow":1.37,"yearHigh":3.08,"marketCap":null,"consecutiveDays":2,"totalChangePct":-12.66,"direction":"DOWN"},{"code":"IQST","name":"IQST","market":"US","currentPrice":1.09,"currentChangePct":-2.68,"yearLow":0.87,"yearHigh":10.374,"marketCap":null,"consecutiveDays":2,"totalChangePct":-12.1,"direction":"DOWN"},{"code":"SEGG","name":"SEGG","market":"US","currentPrice":0.7389,"currentChangePct":-5.39,"yearLow":0.46,"yearHigh":12.4,"marketCap":null,"consecutiveDays":2,"totalChangePct":-11.93,"direction":"DOWN"},{"code":"ILLR","name":"ILLR","market":"US","currentPrice":1.29,"currentChangePct":-10.42,"yearLow":0.01,"yearHigh":17.3,"marketCap":null,"consecutiveDays":2,"totalChangePct":-11.64,"direction":"DOWN"},{"code":"INUV","name":"INUV","market":"US","currentPrice":1.08,"currentChangePct":-7.69,"yearLow":1.0,"yearHigh":5.93,"marketCap":null,"consecutiveDays":2,"totalChangePct":-10.74,"direction":"DOWN"},{"code":"DTCX","name":"DTCX","market":"US","currentPrice":1.93,"currentChangePct":-3.5,"yearLow":1.51,"yearHigh":16.49,"marketCap":null,"consecutiveDays":2,"totalChangePct":-10.65,"direction":"DOWN"},{"code":"TVRD","name":"TVRD","market":"US","currentPrice":2.86,"currentChangePct":-2.39,"yearLow":1.5,"yearHigh":43.65,"marketCap":null,"consecutiveDays":2,"totalChangePct":-10.63,"direction":"DOWN"},{"code":"CLNE","name":"CLNE","market":"US","currentPrice":2.13,"currentChangePct":-1.84,"yearLow":1.66,"yearHigh":3.11,"marketCap":null,"consecutiveDays":2,"totalChangePct":-10.5,"direction":"DOWN"},{"code":"CAST","name":"CAST","market":"US","currentPrice":2.37,"currentChangePct":-7.06,"yearLow":0.5,"yearHigh":33.0,"marketCap":null,"consecutiveDays":2,"totalChangePct":-10.23,"direction":"DOWN"},{"code":"ILAG","name":"ILAG","market":"US","currentPrice":3.36,"currentChangePct":-8.45,"yearLow":2.04,"yearHigh":9.56,"marketCap":null,"consecutiveDays":2,"totalChangePct":-9.92,"direction":"DOWN"},{"code":"OTLY","name":"OTLY","market":"US","currentPrice":9.05,"currentChangePct":-8.4,"yearLow":8.01,"yearHigh":18.84,"marketCap":null,"consecutiveDays":2,"totalChangePct":-9.86,"direction":"DOWN"},{"code":"QLYS","name":"QLYS","market":"US","currentPrice":143.78,"currentChangePct":-8.05,"yearLow":74.51,"yearHigh":167.86,"marketCap":null,"consecutiveDays":2,"totalChangePct":-9.82,"direction":"DOWN"},{"code":"BATL","name":"BATL","market":"US","currentPrice":1.57,"currentChangePct":-4.85,"yearLow":1.0,"yearHigh":29.7,"marketCap":null,"consecutiveDays":2,"totalChangePct":-9.77,"direction":"DOWN"},{"code":"SKIN","name":"SKIN","market":"US","currentPrice":0.7616,"currentChangePct":-3.35,"yearLow":0.551,"yearHigh":2.69,"marketCap":null,"consecutiveDays":2,"totalChangePct":-9.76,"direction":"DOWN"},{"code":"VICR","name":"VICR","market":"US","currentPrice":214.7,"currentChangePct":-7.05,"yearLow":41.76,"yearHigh":382.65,"marketCap":null,"consecutiveDays":2,"totalChangePct":-9.65,"direction":"DOWN"},{"code":"SGMT","name":"SGMT","market":"US","currentPrice":7.07,"currentChangePct":-1.26,"yearLow":4.5,"yearHigh":11.41,"marketCap":null,"consecutiveDays":2,"totalChangePct":-9.59,"direction":"DOWN"},{"code":"TRAW","name":"TRAW","market":"US","currentPrice":0.6066,"currentChangePct":-0.56,"yearLow":0.6,"yearHigh":3.27,"marketCap":null,"consecutiveDays":2,"totalChangePct":-9.46,"direction":"DOWN"},{"code":"MYSE","name":"MYSE","market":"US","currentPrice":2.59,"currentChangePct":-7.17,"yearLow":1.31,"yearHigh":5.77,"marketCap":null,"consecutiveDays":2,"totalChangePct":-9.12,"direction":"DOWN"},{"code":"AUID","name":"AUID","market":"US","currentPrice":0.817,"currentChangePct":-6.09,"yearLow":0.761,"yearHigh":4.7,"marketCap":null,"consecutiveDays":2,"totalChangePct":-9.02,"direction":"DOWN"},{"code":"KMTS","name":"KMTS","market":"US","currentPrice":22.24,"currentChangePct":-4.3,"yearLow":14.1,"yearHigh":30.0,"marketCap":null,"consecutiveDays":2,"totalChangePct":-8.93,"direction":"DOWN"},{"code":"HTLM","name":"HTLM","market":"US","currentPrice":1.84,"currentChangePct":-6.6,"yearLow":1.56,"yearHigh":4.19,"marketCap":null,"consecutiveDays":2,"totalChangePct":-8.68,"direction":"DOWN"},{"code":"MVO","name":"MVO","market":"US","currentPrice":0.612,"currentChangePct":-2.87,"yearLow":0.6,"yearHigh":6.19,"marketCap":null,"consecutiveDays":2,"totalChangePct":-8.67,"direction":"DOWN"},{"code":"SENEB","name":"SENEB","market":"US","currentPrice":171.23,"currentChangePct":-5.78,"yearLow":103.07,"yearHigh":181.48,"marketCap":null,"consecutiveDays":2,"totalChangePct":-8.42,"direction":"DOWN"},{"code":"BRZE","name":"BRZE","market":"US","currentPrice":24.28,"currentChangePct":-7.29,"yearLow":15.26,"yearHigh":37.327,"marketCap":null,"consecutiveDays":2,"totalChangePct":-8.38,"direction":"DOWN"},{"code":"LFWD","name":"LFWD","market":"US","currentPrice":7.25,"currentChangePct":-3.97,"yearLow":4.14,"yearHigh":10.56,"marketCap":null,"consecutiveDays":2,"totalChangePct":-8.34,"direction":"DOWN"},{"code":"IPST","name":"IPST","market":"US","currentPrice":2.31,"currentChangePct":-3.35,"yearLow":2.1,"yearHigh":532.0,"marketCap":null,"consecutiveDays":2,"totalChangePct":-8.33,"direction":"DOWN"},{"code":"AMPG","name":"AMPG","market":"US","currentPrice":6.09,"currentChangePct":-2.09,"yearLow":1.64,"yearHigh":10.11,"marketCap":null,"consecutiveDays":2,"totalChangePct":-8.28,"direction":"DOWN"},{"code":"DKI","name":"DKI","market":"US","currentPrice":4.68,"currentChangePct":-2.7,"yearLow":0.285,"yearHigh":15.0,"marketCap":null,"consecutiveDays":2,"totalChangePct":-8.24,"direction":"DOWN"},{"code":"APRE","name":"APRE","market":"US","currentPrice":0.652,"currentChangePct":-2.54,"yearLow":0.548,"yearHigh":2.22,"marketCap":null,"consecutiveDays":2,"totalChangePct":-8.17,"direction":"DOWN"},{"code":"MGY","name":"MGY","market":"US","currentPrice":25.09,"currentChangePct":-1.72,"yearLow":21.065,"yearHigh":32.76,"marketCap":null,"consecutiveDays":2,"totalChangePct":-7.96,"direction":"DOWN"},{"code":"VEEA","name":"VEEA","market":"US","currentPrice":0.1789,"currentChangePct":-0.61,"yearLow":0.1603,"yearHigh":1.86,"marketCap":null,"consecutiveDays":2,"totalChangePct":-7.78,"direction":"DOWN"},{"code":"MYPS","name":"MYPS","market":"US","currentPrice":0.762,"currentChangePct":-6.73,"yearLow":0.402,"yearHigh":1.31,"marketCap":null,"consecutiveDays":2,"totalChangePct":-7.75,"direction":"DOWN"},{"code":"GNLN","name":"GNLN","market":"US","currentPrice":2.3,"currentChangePct":-2.54,"yearLow":2.096,"yearHigh":42.56,"marketCap":null,"consecutiveDays":2,"totalChangePct":-7.63,"direction":"DOWN"},{"code":"ANPA","name":"ANPA","market":"US","currentPrice":4.0,"currentChangePct":-5.88,"yearLow":3.6,"yearHigh":180.639,"marketCap":null,"consecutiveDays":2,"totalChangePct":-7.62,"direction":"DOWN"},{"code":"BUUU","name":"BUUU","market":"US","currentPrice":20.25,"currentChangePct":-7.53,"yearLow":3.67,"yearHigh":27.45,"marketCap":null,"consecutiveDays":2,"totalChangePct":-7.58,"direction":"DOWN"},{"code":"NXGL","name":"NXGL","market":"US","currentPrice":0.4353,"currentChangePct":-2.4,"yearLow":0.421,"yearHigh":2.89,"marketCap":null,"consecutiveDays":2,"totalChangePct":-7.58,"direction":"DOWN"},{"code":"HUBC","name":"HUBC","market":"US","currentPrice":1.11,"currentChangePct":-3.48,"yearLow":1.035,"yearHigh":65025.0,"marketCap":null,"consecutiveDays":2,"totalChangePct":-7.5,"direction":"DOWN"},{"code":"ENRD","name":"ENRD","market":"US","currentPrice":4.63,"currentChangePct":-5.12,"yearLow":4.63,"yearHigh":34.0,"marketCap":null,"consecutiveDays":2,"totalChangePct":-7.4,"direction":"DOWN"},{"code":"SMXT","name":"SMXT","market":"US","currentPrice":0.331,"currentChangePct":-6.23,"yearLow":0.293,"yearHigh":2.5,"marketCap":null,"consecutiveDays":2,"totalChangePct":-7.28,"direction":"DOWN"},{"code":"ACOG","name":"ACOG","market":"US","currentPrice":7.89,"currentChangePct":-5.4,"yearLow":4.5,"yearHigh":10.244,"marketCap":null,"consecutiveDays":2,"totalChangePct":-7.18,"direction":"DOWN"},{"code":"NMG","name":"NMG","market":"US","currentPrice":1.32,"currentChangePct":-2.94,"yearLow":1.31,"yearHigh":6.06,"marketCap":null,"consecutiveDays":2,"totalChangePct":-7.04,"direction":"DOWN"},{"code":"SAFX","name":"SAFX","market":"US","currentPrice":0.4351,"currentChangePct":-0.21,"yearLow":0.119,"yearHigh":1.87,"marketCap":null,"consecutiveDays":2,"totalChangePct":-7.03,"direction":"DOWN"},{"code":"BNTC","name":"BNTC","market":"US","currentPrice":11.89,"currentChangePct":-0.67,"yearLow":9.85,"yearHigh":16.76,"marketCap":null,"consecutiveDays":2,"totalChangePct":-6.96,"direction":"DOWN"},{"code":"SORA","name":"SORA","market":"US","currentPrice":1.61,"currentChangePct":-4.73,"yearLow":1.25,"yearHigh":7.2,"marketCap":null,"consecutiveDays":2,"totalChangePct":-6.94,"direction":"DOWN"},{"code":"LIQT","name":"LIQT","market":"US","currentPrice":0.6423,"currentChangePct":-1.18,"yearLow":0.62,"yearHigh":3.35,"marketCap":null,"consecutiveDays":2,"totalChangePct":-6.91,"direction":"DOWN"},{"code":"CIRC","name":"CIRC","market":"US","currentPrice":0.7188,"currentChangePct":-6.41,"yearLow":0.414,"yearHigh":5.25,"marketCap":null,"consecutiveDays":2,"totalChangePct":-6.89,"direction":"DOWN"},{"code":"LFT","name":"LFT","market":"US","currentPrice":0.8659,"currentChangePct":-0.47,"yearLow":0.844,"yearHigh":2.44,"marketCap":null,"consecutiveDays":2,"totalChangePct":-6.89,"direction":"DOWN"},{"code":"NCEL","name":"NCEL","market":"US","currentPrice":3.81,"currentChangePct":-4.03,"yearLow":1.83,"yearHigh":28.03,"marketCap":null,"consecutiveDays":2,"totalChangePct":-6.85,"direction":"DOWN"},{"code":"BGMS","name":"BGMS","market":"US","currentPrice":0.885,"currentChangePct":-1.67,"yearLow":0.57,"yearHigh":19.87,"marketCap":null,"consecutiveDays":2,"totalChangePct":-6.84,"direction":"DOWN"},{"code":"HLP","name":"HLP","market":"US","currentPrice":1.09,"currentChangePct":-0.91,"yearLow":0.342,"yearHigh":1.72,"marketCap":null,"consecutiveDays":2,"totalChangePct":-6.84,"direction":"DOWN"},{"code":"SFHG","name":"SFHG","market":"US","currentPrice":2.45,"currentChangePct":-0.81,"yearLow":1.6,"yearHigh":4.95,"marketCap":null,"consecutiveDays":2,"totalChangePct":-6.84,"direction":"DOWN"},{"code":"TCI","name":"TCI","market":"US","currentPrice":42.56,"currentChangePct":-1.8,"yearLow":31.48,"yearHigh":59.65,"marketCap":null,"consecutiveDays":2,"totalChangePct":-6.69,"direction":"DOWN"},{"code":"LX","name":"LX","market":"US","currentPrice":1.44,"currentChangePct":-0.69,"yearLow":1.405,"yearHigh":7.985,"marketCap":null,"consecutiveDays":2,"totalChangePct":-6.49,"direction":"DOWN"},{"code":"WKSP","name":"WKSP","market":"US","currentPrice":0.664,"currentChangePct":-2.32,"yearLow":0.569,"yearHigh":4.3,"marketCap":null,"consecutiveDays":2,"totalChangePct":-6.45,"direction":"DOWN"},{"code":"MWG","name":"MWG","market":"US","currentPrice":1.301,"currentChangePct":-5.0,"yearLow":1.1,"yearHigh":6.05,"marketCap":null,"consecutiveDays":2,"totalChangePct":-6.37,"direction":"DOWN"},{"code":"MLSS","name":"MLSS","market":"US","currentPrice":0.412,"currentChangePct":-4.19,"yearLow":0.22,"yearHigh":0.68,"marketCap":null,"consecutiveDays":2,"totalChangePct":-6.36,"direction":"DOWN"},{"code":"HROW","name":"HROW","market":"US","currentPrice":43.71,"currentChangePct":-1.66,"yearLow":28.54,"yearHigh":54.85,"marketCap":null,"consecutiveDays":2,"totalChangePct":-6.3,"direction":"DOWN"},{"code":"EPC","name":"EPC","market":"US","currentPrice":27.8,"currentChangePct":-2.76,"yearLow":15.73,"yearHigh":29.85,"marketCap":null,"consecutiveDays":2,"totalChangePct":-6.27,"direction":"DOWN"},{"code":"TYL","name":"TYL","market":"US","currentPrice":299.74,"currentChangePct":-5.73,"yearLow":270.71,"yearHigh":621.34,"marketCap":null,"consecutiveDays":2,"totalChangePct":-6.19,"direction":"DOWN"},{"code":"EVCM","name":"EVCM","market":"US","currentPrice":11.3,"currentChangePct":-4.4,"yearLow":7.66,"yearHigh":14.41,"marketCap":null,"consecutiveDays":2,"totalChangePct":-6.15,"direction":"DOWN"},{"code":"PUSA","name":"PUSA","market":"US","currentPrice":3.41,"currentChangePct":-2.29,"yearLow":0.605,"yearHigh":8.25,"marketCap":null,"consecutiveDays":2,"totalChangePct":-6.06,"direction":"DOWN"},{"code":"REED","name":"REED","market":"US","currentPrice":0.94,"currentChangePct":-2.08,"yearLow":0.8,"yearHigh":12.0,"marketCap":null,"consecutiveDays":2,"totalChangePct":-6.0,"direction":"DOWN"},{"code":"LANV","name":"LANV","market":"US","currentPrice":1.26,"currentChangePct":-4.55,"yearLow":1.03,"yearHigh":2.54,"marketCap":null,"consecutiveDays":2,"totalChangePct":-5.97,"direction":"DOWN"},{"code":"PEPG","name":"PEPG","market":"US","currentPrice":2.12,"currentChangePct":-3.64,"yearLow":1.01,"yearHigh":7.8,"marketCap":null,"consecutiveDays":2,"totalChangePct":-5.78,"direction":"DOWN"},{"code":"CMMB","name":"CMMB","market":"US","currentPrice":1.47,"currentChangePct":-2.0,"yearLow":1.35,"yearHigh":4.84,"marketCap":null,"consecutiveDays":2,"totalChangePct":-5.77,"direction":"DOWN"},{"code":"HAL","name":"HAL","market":"US","currentPrice":33.19,"currentChangePct":-5.47,"yearLow":20.17,"yearHigh":43.59,"marketCap":null,"consecutiveDays":2,"totalChangePct":-5.76,"direction":"DOWN"},{"code":"AMWL","name":"AMWL","market":"US","currentPrice":12.47,"currentChangePct":-0.87,"yearLow":3.71,"yearHigh":13.45,"marketCap":null,"consecutiveDays":2,"totalChangePct":-5.74,"direction":"DOWN"},{"code":"VALU","name":"VALU","market":"US","currentPrice":38.65,"currentChangePct":-2.05,"yearLow":32.0,"yearHigh":41.18,"marketCap":null,"consecutiveDays":2,"totalChangePct":-5.73,"direction":"DOWN"},{"code":"CWD","name":"CWD","market":"US","currentPrice":0.73,"currentChangePct":-1.11,"yearLow":0.575,"yearHigh":48.0,"marketCap":null,"consecutiveDays":2,"totalChangePct":-5.71,"direction":"DOWN"},{"code":"TLS","name":"TLS","market":"US","currentPrice":4.46,"currentChangePct":-2.41,"yearLow":2.37,"yearHigh":8.36,"marketCap":null,"consecutiveDays":2,"totalChangePct":-5.71,"direction":"DOWN"},{"code":"BAK","name":"BAK","market":"US","currentPrice":2.32,"currentChangePct":-1.69,"yearLow":2.25,"yearHigh":5.395,"marketCap":null,"consecutiveDays":2,"totalChangePct":-5.69,"direction":"DOWN"},{"code":"SDST","name":"SDST","market":"US","currentPrice":1.66,"currentChangePct":-2.35,"yearLow":1.52,"yearHigh":7.67,"marketCap":null,"consecutiveDays":2,"totalChangePct":-5.68,"direction":"DOWN"},{"code":"BMM","name":"BMM","market":"US","currentPrice":5.44,"currentChangePct":-2.94,"yearLow":3.47,"yearHigh":8.63,"marketCap":null,"consecutiveDays":2,"totalChangePct":-5.56,"direction":"DOWN"},{"code":"PYXS","name":"PYXS","market":"US","currentPrice":2.23,"currentChangePct":-0.89,"yearLow":0.97,"yearHigh":5.55,"marketCap":null,"consecutiveDays":2,"totalChangePct":-5.51,"direction":"DOWN"},{"code":"FA","name":"FA","market":"US","currentPrice":21.12,"currentChangePct":-5.29,"yearLow":8.82,"yearHigh":22.78,"marketCap":null,"consecutiveDays":2,"totalChangePct":-5.5,"direction":"DOWN"},{"code":"CELZ","name":"CELZ","market":"US","currentPrice":0.831,"currentChangePct":-3.72,"yearLow":0.79,"yearHigh":6.25,"marketCap":null,"consecutiveDays":2,"totalChangePct":-5.47,"direction":"DOWN"},{"code":"PPBT","name":"PPBT","market":"US","currentPrice":1.39,"currentChangePct":-4.14,"yearLow":1.35,"yearHigh":29.0,"marketCap":null,"consecutiveDays":2,"totalChangePct":-5.45,"direction":"DOWN"},{"code":"HONA","name":"HONA","market":"US","currentPrice":200.14,"currentChangePct":-1.15,"yearLow":195.16,"yearHigh":297.5,"marketCap":null,"consecutiveDays":2,"totalChangePct":-5.43,"direction":"DOWN"},{"code":"NAMI","name":"NAMI","market":"US","currentPrice":3.2,"currentChangePct":-0.62,"yearLow":3.1,"yearHigh":51.25,"marketCap":null,"consecutiveDays":2,"totalChangePct":-5.33,"direction":"DOWN"},{"code":"AS","name":"AS","market":"US","currentPrice":34.5,"currentChangePct":-5.06,"yearLow":28.92,"yearHigh":42.76,"marketCap":null,"consecutiveDays":2,"totalChangePct":-5.32,"direction":"DOWN"},{"code":"SRG","name":"SRG","market":"US","currentPrice":2.5,"currentChangePct":-2.34,"yearLow":2.31,"yearHigh":4.56,"marketCap":null,"consecutiveDays":2,"totalChangePct":-5.3,"direction":"DOWN"},{"code":"SDA","name":"SDA","market":"US","currentPrice":0.78,"currentChangePct":-4.65,"yearLow":0.47,"yearHigh":2.93,"marketCap":null,"consecutiveDays":2,"totalChangePct":-5.22,"direction":"DOWN"},{"code":"OPTH","name":"OPTH","market":"US","currentPrice":4.75,"currentChangePct":-0.84,"yearLow":4.0,"yearHigh":6.4,"marketCap":null,"consecutiveDays":2,"totalChangePct":-5.19,"direction":"DOWN"},{"code":"VRME","name":"VRME","market":"US","currentPrice":0.63,"currentChangePct":-4.8,"yearLow":0.59,"yearHigh":1.51,"marketCap":null,"consecutiveDays":2,"totalChangePct":-5.19,"direction":"DOWN"},{"code":"WING","name":"WING","market":"US","currentPrice":134.95,"currentChangePct":-4.36,"yearLow":116.35,"yearHigh":381.45,"marketCap":null,"consecutiveDays":2,"totalChangePct":-5.19,"direction":"DOWN"},{"code":"NTRP","name":"NTRP","market":"US","currentPrice":1.84,"currentChangePct":-3.16,"yearLow":1.61,"yearHigh":5.2,"marketCap":null,"consecutiveDays":2,"totalChangePct":-5.15,"direction":"DOWN"},{"code":"OKTA","name":"OKTA","market":"US","currentPrice":141.71,"currentChangePct":-4.51,"yearLow":62.66,"yearHigh":157.0,"marketCap":null,"consecutiveDays":2,"totalChangePct":-5.12,"direction":"DOWN"},{"code":"TWLO","name":"TWLO","market":"US","currentPrice":196.22,"currentChangePct":-4.39,"yearLow":91.84,"yearHigh":238.48,"marketCap":null,"consecutiveDays":2,"totalChangePct":-5.11,"direction":"DOWN"},{"code":"SCKT","name":"SCKT","market":"US","currentPrice":0.484,"currentChangePct":-3.2,"yearLow":0.47,"yearHigh":1.36,"marketCap":null,"consecutiveDays":2,"totalChangePct":-5.1,"direction":"DOWN"},{"code":"ERIE","name":"ERIE","market":"US","currentPrice":215.82,"currentChangePct":-4.08,"yearLow":204.63,"yearHigh":380.67,"marketCap":null,"consecutiveDays":2,"totalChangePct":-5.05,"direction":"DOWN"},{"code":"GHG","name":"GHG","market":"US","currentPrice":1.13,"currentChangePct":-1.74,"yearLow":1.11,"yearHigh":2.776,"marketCap":null,"consecutiveDays":2,"totalChangePct":-5.04,"direction":"DOWN"},{"code":"NEPH","name":"NEPH","market":"US","currentPrice":3.59,"currentChangePct":-2.45,"yearLow":2.66,"yearHigh":6.42,"marketCap":null,"consecutiveDays":2,"totalChangePct":-5.03,"direction":"DOWN"},{"code":"DCBO","name":"DCBO","market":"US","currentPrice":19.36,"currentChangePct":-0.62,"yearLow":14.39,"yearHigh":33.42,"marketCap":null,"consecutiveDays":2,"totalChangePct":-5.0,"direction":"DOWN"},{"code":"GWRE","name":"GWRE","market":"US","currentPrice":142.53,"currentChangePct":-4.46,"yearLow":102.3,"yearHigh":272.6,"marketCap":null,"consecutiveDays":2,"totalChangePct":-4.99,"direction":"DOWN"},{"code":"YSWY","name":"YSWY","market":"US","currentPrice":19.87,"currentChangePct":-1.39,"yearLow":18.92,"yearHigh":29.08,"marketCap":null,"consecutiveDays":2,"totalChangePct":-4.88,"direction":"DOWN"},{"code":"AACG","name":"AACG","market":"US","currentPrice":0.933,"currentChangePct":-1.84,"yearLow":0.74,"yearHigh":2.58,"marketCap":null,"consecutiveDays":2,"totalChangePct":-4.85,"direction":"DOWN"},{"code":"CHKP","name":"CHKP","market":"US","currentPrice":130.46,"currentChangePct":-3.88,"yearLow":112.23,"yearHigh":225.23,"marketCap":null,"consecutiveDays":2,"totalChangePct":-4.84,"direction":"DOWN"},{"code":"BIRK","name":"BIRK","market":"US","currentPrice":42.22,"currentChangePct":-1.29,"yearLow":31.12,"yearHigh":53.53,"marketCap":null,"consecutiveDays":2,"totalChangePct":-4.82,"direction":"DOWN"},{"code":"DAIO","name":"DAIO","market":"US","currentPrice":3.19,"currentChangePct":-1.24,"yearLow":2.16,"yearHigh":4.49,"marketCap":null,"consecutiveDays":2,"totalChangePct":-4.78,"direction":"DOWN"},{"code":"SBAC","name":"SBAC","market":"US","currentPrice":176.82,"currentChangePct":-2.83,"yearLow":162.41,"yearHigh":243.16,"marketCap":null,"consecutiveDays":2,"totalChangePct":-4.78,"direction":"DOWN"},{"code":"ESLA","name":"ESLA","market":"US","currentPrice":0.8,"currentChangePct":-3.03,"yearLow":0.73,"yearHigh":3.15,"marketCap":null,"consecutiveDays":2,"totalChangePct":-4.76,"direction":"DOWN"},{"code":"BEEP","name":"BEEP","market":"US","currentPrice":1.85,"currentChangePct":-1.6,"yearLow":1.29,"yearHigh":4.065,"marketCap":null,"consecutiveDays":2,"totalChangePct":-4.64,"direction":"DOWN"},{"code":"SPT","name":"SPT","market":"US","currentPrice":8.22,"currentChangePct":-2.26,"yearLow":4.92,"yearHigh":19.51,"marketCap":null,"consecutiveDays":2,"totalChangePct":-4.64,"direction":"DOWN"},{"code":"WU","name":"WU","market":"US","currentPrice":8.47,"currentChangePct":-2.19,"yearLow":6.91,"yearHigh":10.35,"marketCap":null,"consecutiveDays":2,"totalChangePct":-4.62,"direction":"DOWN"},{"code":"PANW","name":"PANW","market":"US","currentPrice":342.15,"currentChangePct":-1.87,"yearLow":139.57,"yearHigh":368.8,"marketCap":null,"consecutiveDays":2,"totalChangePct":-4.61,"direction":"DOWN"},{"code":"PMN","name":"PMN","market":"US","currentPrice":14.49,"currentChangePct":-3.91,"yearLow":6.27,"yearHigh":27.4,"marketCap":null,"consecutiveDays":2,"totalChangePct":-4.61,"direction":"DOWN"},{"code":"CNS","name":"CNS","market":"US","currentPrice":80.79,"currentChangePct":-2.07,"yearLow":58.39,"yearHigh":84.93,"marketCap":null,"consecutiveDays":2,"totalChangePct":-4.56,"direction":"DOWN"},{"code":"NVRI","name":"NVRI","market":"US","currentPrice":21.87,"currentChangePct":-0.95,"yearLow":7.7,"yearHigh":23.56,"marketCap":null,"consecutiveDays":2,"totalChangePct":-4.54,"direction":"DOWN"},{"code":"SPFI","name":"SPFI","market":"US","currentPrice":43.88,"currentChangePct":-0.79,"yearLow":35.34,"yearHigh":46.94,"marketCap":null,"consecutiveDays":2,"totalChangePct":-4.53,"direction":"DOWN"},{"code":"MIRA","name":"MIRA","market":"US","currentPrice":0.917,"currentChangePct":-0.36,"yearLow":0.896,"yearHigh":2.45,"marketCap":null,"consecutiveDays":2,"totalChangePct":-4.51,"direction":"DOWN"},{"code":"KRYS","name":"KRYS","market":"US","currentPrice":339.06,"currentChangePct":-0.05,"yearLow":130.5,"yearHigh":382.535,"marketCap":null,"consecutiveDays":2,"totalChangePct":-4.45,"direction":"DOWN"},{"code":"QRHC","name":"QRHC","market":"US","currentPrice":1.29,"currentChangePct":-1.53,"yearLow":0.81,"yearHigh":2.41,"marketCap":null,"consecutiveDays":2,"totalChangePct":-4.44,"direction":"DOWN"},{"code":"PODC","name":"PODC","market":"US","currentPrice":3.9,"currentChangePct":-2.5,"yearLow":1.3,"yearHigh":5.2,"marketCap":null,"consecutiveDays":2,"totalChangePct":-4.41,"direction":"DOWN"},{"code":"DKNG","name":"DKNG","market":"US","currentPrice":23.85,"currentChangePct":-1.93,"yearLow":20.46,"yearHigh":48.78,"marketCap":null,"consecutiveDays":2,"totalChangePct":-4.37,"direction":"DOWN"},{"code":"UCL","name":"UCL","market":"US","currentPrice":0.88,"currentChangePct":-0.45,"yearLow":0.88,"yearHigh":4.19,"marketCap":null,"consecutiveDays":2,"totalChangePct":-4.35,"direction":"DOWN"},{"code":"SN","name":"SN","market":"US","currentPrice":147.82,"currentChangePct":-3.28,"yearLow":83.12,"yearHigh":156.865,"marketCap":null,"consecutiveDays":2,"totalChangePct":-4.34,"direction":"DOWN"},{"code":"GCLWW","name":"GCLWW","market":"US","currentPrice":0.0199,"currentChangePct":-3.86,"yearLow":0.0198,"yearHigh":0.051,"marketCap":null,"consecutiveDays":2,"totalChangePct":-4.33,"direction":"DOWN"},{"code":"CNDT","name":"CNDT","market":"US","currentPrice":1.55,"currentChangePct":-3.13,"yearLow":1.15,"yearHigh":2.98,"marketCap":null,"consecutiveDays":2,"totalChangePct":-4.32,"direction":"DOWN"},{"code":"MGLD","name":"MGLD","market":"US","currentPrice":1.11,"currentChangePct":-1.77,"yearLow":0.642,"yearHigh":1.38,"marketCap":null,"consecutiveDays":2,"totalChangePct":-4.31,"direction":"DOWN"},{"code":"CALX","name":"CALX","market":"US","currentPrice":37.47,"currentChangePct":-2.29,"yearLow":34.27,"yearHigh":71.22,"marketCap":null,"consecutiveDays":2,"totalChangePct":-4.27,"direction":"DOWN"},{"code":"ADBE","name":"ADBE","market":"US","currentPrice":227.16,"currentChangePct":-3.23,"yearLow":190.12,"yearHigh":376.16,"marketCap":null,"consecutiveDays":2,"totalChangePct":-4.25,"direction":"DOWN"},{"code":"FWONK","name":"FWONK","market":"US","currentPrice":97.915,"currentChangePct":-1.3,"yearLow":80.15,"yearHigh":109.363,"marketCap":null,"consecutiveDays":2,"totalChangePct":-4.19,"direction":"DOWN"},{"code":"ESRT","name":"ESRT","market":"US","currentPrice":5.53,"currentChangePct":-1.25,"yearLow":4.87,"yearHigh":8.07,"marketCap":null,"consecutiveDays":2,"totalChangePct":-4.16,"direction":"DOWN"},{"code":"VRSN","name":"VRSN","market":"US","currentPrice":266.15,"currentChangePct":-4.13,"yearLow":208.86,"yearHigh":312.48,"marketCap":null,"consecutiveDays":2,"totalChangePct":-4.15,"direction":"DOWN"},{"code":"DKS","name":"DKS","market":"US","currentPrice":208.41,"currentChangePct":-2.76,"yearLow":186.67,"yearHigh":244.38,"marketCap":null,"consecutiveDays":2,"totalChangePct":-4.12,"direction":"DOWN"},{"code":"FWONA","name":"FWONA","market":"US","currentPrice":90.12,"currentChangePct":-1.15,"yearLow":73.7,"yearHigh":99.52,"marketCap":null,"consecutiveDays":2,"totalChangePct":-4.01,"direction":"DOWN"},{"code":"SDEV","name":"SDEV","market":"US","currentPrice":1.2,"currentChangePct":-3.23,"yearLow":1.01,"yearHigh":99.75,"marketCap":null,"consecutiveDays":2,"totalChangePct":-4.0,"direction":"DOWN"},{"code":"YJ","name":"YJ","market":"US","currentPrice":1.44,"currentChangePct":-1.37,"yearLow":1.11,"yearHigh":2.67,"marketCap":null,"consecutiveDays":2,"totalChangePct":-4.0,"direction":"DOWN"},{"code":"HRB","name":"HRB","market":"US","currentPrice":40.42,"currentChangePct":-3.07,"yearLow":28.16,"yearHigh":56.76,"marketCap":null,"consecutiveDays":2,"totalChangePct":-3.94,"direction":"DOWN"},{"code":"AMT","name":"AMT","market":"US","currentPrice":163.39,"currentChangePct":-2.2,"yearLow":160.06,"yearHigh":234.33,"marketCap":null,"consecutiveDays":2,"totalChangePct":-3.92,"direction":"DOWN"},{"code":"DBX","name":"DBX","market":"US","currentPrice":29.42,"currentChangePct":-3.64,"yearLow":21.695,"yearHigh":32.4,"marketCap":null,"consecutiveDays":2,"totalChangePct":-3.92,"direction":"DOWN"},{"code":"ARES","name":"ARES","market":"US","currentPrice":120.78,"currentChangePct":-0.4,"yearLow":95.8,"yearHigh":195.26,"marketCap":null,"consecutiveDays":2,"totalChangePct":-3.9,"direction":"DOWN"},{"code":"ASAN","name":"ASAN","market":"US","currentPrice":7.39,"currentChangePct":-2.76,"yearLow":5.38,"yearHigh":15.71,"marketCap":null,"consecutiveDays":2,"totalChangePct":-3.9,"direction":"DOWN"},{"code":"NNDM","name":"NNDM","market":"US","currentPrice":1.49,"currentChangePct":-2.61,"yearLow":1.19,"yearHigh":2.32,"marketCap":null,"consecutiveDays":2,"totalChangePct":-3.87,"direction":"DOWN"},{"code":"PFG","name":"PFG","market":"US","currentPrice":109.57,"currentChangePct":-2.22,"yearLow":75.0,"yearHigh":114.9,"marketCap":null,"consecutiveDays":2,"totalChangePct":-3.84,"direction":"DOWN"},{"code":"PRLD","name":"PRLD","market":"US","currentPrice":4.04,"currentChangePct":-0.49,"yearLow":0.75,"yearHigh":5.69,"marketCap":null,"consecutiveDays":2,"totalChangePct":-3.81,"direction":"DOWN"},{"code":"KPRX","name":"KPRX","market":"US","currentPrice":2.53,"currentChangePct":-2.69,"yearLow":1.765,"yearHigh":3.15,"marketCap":null,"consecutiveDays":2,"totalChangePct":-3.8,"direction":"DOWN"},{"code":"ATCX","name":"ATCX","market":"US","currentPrice":3.05,"currentChangePct":-1.13,"yearLow":3.02,"yearHigh":14.01,"marketCap":null,"consecutiveDays":2,"totalChangePct":-3.79,"direction":"DOWN"},{"code":"CCI","name":"CCI","market":"US","currentPrice":76.2,"currentChangePct":-2.53,"yearLow":73.75,"yearHigh":115.76,"marketCap":null,"consecutiveDays":2,"totalChangePct":-3.75,"direction":"DOWN"},{"code":"LXEH","name":"LXEH","market":"US","currentPrice":1.425,"currentChangePct":-2.4,"yearLow":0.832,"yearHigh":32.8,"marketCap":null,"consecutiveDays":2,"totalChangePct":-3.72,"direction":"DOWN"},{"code":"TOON","name":"TOON","market":"US","currentPrice":0.596,"currentChangePct":-2.61,"yearLow":0.504,"yearHigh":1.29,"marketCap":null,"consecutiveDays":2,"totalChangePct":-3.72,"direction":"DOWN"},{"code":"COLD","name":"COLD","market":"US","currentPrice":15.34,"currentChangePct":-0.78,"yearLow":10.1,"yearHigh":17.12,"marketCap":null,"consecutiveDays":2,"totalChangePct":-3.7,"direction":"DOWN"},{"code":"MBI","name":"MBI","market":"US","currentPrice":6.3,"currentChangePct":-1.41,"yearLow":4.72,"yearHigh":8.26,"marketCap":null,"consecutiveDays":2,"totalChangePct":-3.67,"direction":"DOWN"},{"code":"VRXA","name":"VRXA","market":"US","currentPrice":2.1,"currentChangePct":-0.94,"yearLow":1.7,"yearHigh":27.36,"marketCap":null,"consecutiveDays":2,"totalChangePct":-3.67,"direction":"DOWN"},{"code":"KWY","name":"KWY","market":"US","currentPrice":9.3,"currentChangePct":-1.9,"yearLow":9.2,"yearHigh":16.51,"marketCap":null,"consecutiveDays":2,"totalChangePct":-3.63,"direction":"DOWN"},{"code":"WY","name":"WY","market":"US","currentPrice":23.61,"currentChangePct":-1.46,"yearLow":21.16,"yearHigh":27.75,"marketCap":null,"consecutiveDays":2,"totalChangePct":-3.59,"direction":"DOWN"},{"code":"IMAX","name":"IMAX","market":"US","currentPrice":37.85,"currentChangePct":-1.94,"yearLow":24.2,"yearHigh":45.52,"marketCap":null,"consecutiveDays":2,"totalChangePct":-3.57,"direction":"DOWN"},{"code":"NNOX","name":"NNOX","market":"US","currentPrice":1.08,"currentChangePct":-2.7,"yearLow":0.734,"yearHigh":5.55,"marketCap":null,"consecutiveDays":2,"totalChangePct":-3.57,"direction":"DOWN"},{"code":"JRVR","name":"JRVR","market":"US","currentPrice":4.43,"currentChangePct":-3.28,"yearLow":3.76,"yearHigh":7.2,"marketCap":null,"consecutiveDays":2,"totalChangePct":-3.49,"direction":"DOWN"},{"code":"APUS","name":"APUS","market":"US","currentPrice":0.637,"currentChangePct":-1.55,"yearLow":0.6149,"yearHigh":40.31,"marketCap":null,"consecutiveDays":2,"totalChangePct":-3.48,"direction":"DOWN"},{"code":"CVR","name":"CVR","market":"US","currentPrice":9.75,"currentChangePct":-2.01,"yearLow":8.5,"yearHigh":15.0,"marketCap":null,"consecutiveDays":2,"totalChangePct":-3.47,"direction":"DOWN"},{"code":"UFG","name":"UFG","market":"US","currentPrice":0.7135,"currentChangePct":-1.59,"yearLow":0.6,"yearHigh":11.0,"marketCap":null,"consecutiveDays":2,"totalChangePct":-3.45,"direction":"DOWN"},{"code":"VIRC","name":"VIRC","market":"US","currentPrice":5.96,"currentChangePct":-2.13,"yearLow":5.16,"yearHigh":9.09,"marketCap":null,"consecutiveDays":2,"totalChangePct":-3.4,"direction":"DOWN"},{"code":"GLRE","name":"GLRE","market":"US","currentPrice":16.5,"currentChangePct":-2.65,"yearLow":11.57,"yearHigh":19.39,"marketCap":null,"consecutiveDays":2,"totalChangePct":-3.34,"direction":"DOWN"},{"code":"CHH","name":"CHH","market":"US","currentPrice":108.13,"currentChangePct":-1.66,"yearLow":84.04,"yearHigh":136.45,"marketCap":null,"consecutiveDays":2,"totalChangePct":-3.32,"direction":"DOWN"},{"code":"ADSK","name":"ADSK","market":"US","currentPrice":211.15,"currentChangePct":-3.05,"yearLow":185.5,"yearHigh":329.09,"marketCap":null,"consecutiveDays":2,"totalChangePct":-3.3,"direction":"DOWN"},{"code":"ROLR","name":"ROLR","market":"US","currentPrice":6.73,"currentChangePct":-2.89,"yearLow":1.16,"yearHigh":33.68,"marketCap":null,"consecutiveDays":2,"totalChangePct":-3.3,"direction":"DOWN"},{"code":"IBO","name":"IBO","market":"US","currentPrice":0.441,"currentChangePct":-0.9,"yearLow":0.37,"yearHigh":0.83,"marketCap":null,"consecutiveDays":2,"totalChangePct":-3.29,"direction":"DOWN"},{"code":"BROS","name":"BROS","market":"US","currentPrice":66.13,"currentChangePct":-0.18,"yearLow":44.58,"yearHigh":74.65,"marketCap":null,"consecutiveDays":2,"totalChangePct":-3.26,"direction":"DOWN"},{"code":"RDCM","name":"RDCM","market":"US","currentPrice":13.44,"currentChangePct":-1.18,"yearLow":10.41,"yearHigh":16.74,"marketCap":null,"consecutiveDays":2,"totalChangePct":-3.24,"direction":"DOWN"},{"code":"WILC","name":"WILC","market":"US","currentPrice":29.8,"currentChangePct":-2.23,"yearLow":17.66,"yearHigh":37.99,"marketCap":null,"consecutiveDays":2,"totalChangePct":-3.22,"direction":"DOWN"},{"code":"CCIF","name":"CCIF","market":"US","currentPrice":2.71,"currentChangePct":-2.17,"yearLow":2.57,"yearHigh":6.25,"marketCap":null,"consecutiveDays":2,"totalChangePct":-3.21,"direction":"DOWN"},{"code":"INTG","name":"INTG","market":"US","currentPrice":37.83,"currentChangePct":-1.99,"yearLow":9.57,"yearHigh":52.0,"marketCap":null,"consecutiveDays":2,"totalChangePct":-3.2,"direction":"DOWN"},{"code":"CM","name":"CM","market":"US","currentPrice":117.37,"currentChangePct":-0.37,"yearLow":71.0,"yearHigh":122.5,"marketCap":null,"consecutiveDays":2,"totalChangePct":-3.19,"direction":"DOWN"},{"code":"DAVA","name":"DAVA","market":"US","currentPrice":2.73,"currentChangePct":-1.8,"yearLow":2.55,"yearHigh":15.2,"marketCap":null,"consecutiveDays":2,"totalChangePct":-3.19,"direction":"DOWN"},{"code":"SAIC","name":"SAIC","market":"US","currentPrice":111.82,"currentChangePct":-0.75,"yearLow":81.08,"yearHigh":123.41,"marketCap":null,"consecutiveDays":2,"totalChangePct":-3.19,"direction":"DOWN"},{"code":"WSM","name":"WSM","market":"US","currentPrice":221.13,"currentChangePct":-0.99,"yearLow":165.51,"yearHigh":244.65,"marketCap":null,"consecutiveDays":2,"totalChangePct":-3.19,"direction":"DOWN"},{"code":"AGCC","name":"AGCC","market":"US","currentPrice":15.02,"currentChangePct":-2.4,"yearLow":3.66,"yearHigh":25.725,"marketCap":null,"consecutiveDays":2,"totalChangePct":-3.1,"direction":"DOWN"},{"code":"LUCK","name":"LUCK","market":"US","currentPrice":7.18,"currentChangePct":-0.97,"yearLow":5.705,"yearHigh":11.61,"marketCap":null,"consecutiveDays":2,"totalChangePct":-3.1,"direction":"DOWN"},{"code":"SSBI","name":"SSBI","market":"US","currentPrice":13.2,"currentChangePct":-2.8,"yearLow":10.35,"yearHigh":14.0,"marketCap":null,"consecutiveDays":2,"totalChangePct":-3.08,"direction":"DOWN"},{"code":"BL","name":"BL","market":"US","currentPrice":29.36,"currentChangePct":-2.78,"yearLow":24.7,"yearHigh":59.57,"marketCap":null,"consecutiveDays":2,"totalChangePct":-3.07,"direction":"DOWN"},{"code":"TOYO","name":"TOYO","market":"US","currentPrice":5.06,"currentChangePct":-1.75,"yearLow":3.56,"yearHigh":17.43,"marketCap":null,"consecutiveDays":2,"totalChangePct":-3.07,"direction":"DOWN"},{"code":"HBIO","name":"HBIO","market":"US","currentPrice":6.04,"currentChangePct":-1.15,"yearLow":3.8,"yearHigh":9.4,"marketCap":null,"consecutiveDays":2,"totalChangePct":-3.05,"direction":"DOWN"},{"code":"GSIW","name":"GSIW","market":"US","currentPrice":27.16,"currentChangePct":-2.65,"yearLow":8.0,"yearHigh":68.6,"marketCap":null,"consecutiveDays":2,"totalChangePct":-3.03,"direction":"DOWN"},{"code":"RENX","name":"RENX","market":"US","currentPrice":1.92,"currentChangePct":-0.52,"yearLow":1.4,"yearHigh":47.2,"marketCap":null,"consecutiveDays":2,"totalChangePct":-3.03,"direction":"DOWN"},{"code":"BHF","name":"BHF","market":"US","currentPrice":63.63,"currentChangePct":-1.97,"yearLow":42.07,"yearHigh":66.8,"marketCap":null,"consecutiveDays":2,"totalChangePct":-3.02,"direction":"DOWN"},{"code":"AWR","name":"AWR","market":"US","currentPrice":86.6,"currentChangePct":-2.04,"yearLow":69.45,"yearHigh":90.11,"marketCap":null,"consecutiveDays":2,"totalChangePct":-3.0,"direction":"DOWN"},{"code":"VOD","name":"VOD","market":"US","currentPrice":15.27,"currentChangePct":-0.84,"yearLow":10.66,"yearHigh":16.61,"marketCap":null,"consecutiveDays":2,"totalChangePct":-2.99,"direction":"DOWN"},{"code":"VSTS","name":"VSTS","market":"US","currentPrice":16.01,"currentChangePct":-0.81,"yearLow":3.98,"yearHigh":16.9,"marketCap":null,"consecutiveDays":2,"totalChangePct":-2.97,"direction":"DOWN"},{"code":"AD","name":"AD","market":"US","currentPrice":33.97,"currentChangePct":-1.79,"yearLow":33.71,"yearHigh":79.17,"marketCap":null,"consecutiveDays":2,"totalChangePct":-2.94,"direction":"DOWN"},{"code":"ZVIA","name":"ZVIA","market":"US","currentPrice":1.65,"currentChangePct":-1.2,"yearLow":1.11,"yearHigh":3.627,"marketCap":null,"consecutiveDays":2,"totalChangePct":-2.94,"direction":"DOWN"},{"code":"IPDN","name":"IPDN","market":"US","currentPrice":0.408,"currentChangePct":-0.56,"yearLow":0.38,"yearHigh":12.39,"marketCap":null,"consecutiveDays":2,"totalChangePct":-2.93,"direction":"DOWN"},{"code":"VIOT","name":"VIOT","market":"US","currentPrice":0.8057,"currentChangePct":-0.53,"yearLow":0.74,"yearHigh":4.33,"marketCap":null,"consecutiveDays":2,"totalChangePct":-2.93,"direction":"DOWN"},{"code":"ETSY","name":"ETSY","market":"US","currentPrice":81.69,"currentChangePct":-2.78,"yearLow":44.0,"yearHigh":87.14,"marketCap":null,"consecutiveDays":2,"totalChangePct":-2.87,"direction":"DOWN"},{"code":"UNP","name":"UNP","market":"US","currentPrice":293.13,"currentChangePct":-1.05,"yearLow":210.84,"yearHigh":303.15,"marketCap":null,"consecutiveDays":2,"totalChangePct":-2.86,"direction":"DOWN"},{"code":"VRNS","name":"VRNS","market":"US","currentPrice":46.18,"currentChangePct":-2.68,"yearLow":19.7,"yearHigh":63.9,"marketCap":null,"consecutiveDays":2,"totalChangePct":-2.86,"direction":"DOWN"},{"code":"PSO","name":"PSO","market":"US","currentPrice":16.44,"currentChangePct":-1.02,"yearLow":12.02,"yearHigh":17.66,"marketCap":null,"consecutiveDays":2,"totalChangePct":-2.84,"direction":"DOWN"},{"code":"BSVN","name":"BSVN","market":"US","currentPrice":49.52,"currentChangePct":-0.38,"yearLow":38.29,"yearHigh":53.0,"marketCap":null,"consecutiveDays":2,"totalChangePct":-2.83,"direction":"DOWN"},{"code":"LLYVK","name":"LLYVK","market":"US","currentPrice":99.76,"currentChangePct":-1.8,"yearLow":76.935,"yearHigh":108.975,"marketCap":null,"consecutiveDays":2,"totalChangePct":-2.83,"direction":"DOWN"},{"code":"EMA","name":"EMA","market":"US","currentPrice":53.58,"currentChangePct":-1.4,"yearLow":45.77,"yearHigh":55.42,"marketCap":null,"consecutiveDays":2,"totalChangePct":-2.78,"direction":"DOWN"},{"code":"MHLA","name":"MHLA","market":"US","currentPrice":10.5,"currentChangePct":-0.38,"yearLow":9.93,"yearHigh":15.7,"marketCap":null,"consecutiveDays":2,"totalChangePct":-2.78,"direction":"DOWN"},{"code":"LLYVA","name":"LLYVA","market":"US","currentPrice":96.04,"currentChangePct":-1.6,"yearLow":74.38,"yearHigh":105.475,"marketCap":null,"consecutiveDays":2,"totalChangePct":-2.77,"direction":"DOWN"},{"code":"CP","name":"CP","market":"US","currentPrice":91.16,"currentChangePct":-0.55,"yearLow":68.42,"yearHigh":93.95,"marketCap":null,"consecutiveDays":2,"totalChangePct":-2.72,"direction":"DOWN"},{"code":"DOO","name":"DOO","market":"US","currentPrice":59.65,"currentChangePct":-0.45,"yearLow":48.28,"yearHigh":81.89,"marketCap":null,"consecutiveDays":2,"totalChangePct":-2.72,"direction":"DOWN"},{"code":"NMIH","name":"NMIH","market":"US","currentPrice":41.855,"currentChangePct":-1.82,"yearLow":34.84,"yearHigh":43.355,"marketCap":null,"consecutiveDays":2,"totalChangePct":-2.69,"direction":"DOWN"},{"code":"PRGS","name":"PRGS","market":"US","currentPrice":39.46,"currentChangePct":-0.1,"yearLow":23.82,"yearHigh":51.28,"marketCap":null,"consecutiveDays":2,"totalChangePct":-2.69,"direction":"DOWN"},{"code":"FLNT","name":"FLNT","market":"US","currentPrice":3.63,"currentChangePct":-0.82,"yearLow":1.7,"yearHigh":4.15,"marketCap":null,"consecutiveDays":2,"totalChangePct":-2.68,"direction":"DOWN"},{"code":"VRCA","name":"VRCA","market":"US","currentPrice":5.44,"currentChangePct":-0.91,"yearLow":3.28,"yearHigh":9.821,"marketCap":null,"consecutiveDays":2,"totalChangePct":-2.68,"direction":"DOWN"},{"code":"AWK","name":"AWK","market":"US","currentPrice":131.53,"currentChangePct":-1.59,"yearLow":120.57,"yearHigh":147.87,"marketCap":null,"consecutiveDays":2,"totalChangePct":-2.65,"direction":"DOWN"},{"code":"NSC","name":"NSC","market":"US","currentPrice":331.3,"currentChangePct":-1.1,"yearLow":268.23,"yearHigh":342.53,"marketCap":null,"consecutiveDays":2,"totalChangePct":-2.6,"direction":"DOWN"},{"code":"LION","name":"LION","market":"US","currentPrice":13.52,"currentChangePct":-1.24,"yearLow":5.65,"yearHigh":16.7,"marketCap":null,"consecutiveDays":2,"totalChangePct":-2.59,"direction":"DOWN"},{"code":"ACI","name":"ACI","market":"US","currentPrice":14.72,"currentChangePct":-1.6,"yearLow":13.165,"yearHigh":20.91,"marketCap":null,"consecutiveDays":2,"totalChangePct":-2.58,"direction":"DOWN"},{"code":"BAER","name":"BAER","market":"US","currentPrice":1.89,"currentChangePct":-2.07,"yearLow":1.47,"yearHigh":3.44,"marketCap":null,"consecutiveDays":2,"totalChangePct":-2.58,"direction":"DOWN"},{"code":"PM","name":"PM","market":"US","currentPrice":188.04,"currentChangePct":-2.43,"yearLow":142.11,"yearHigh":194.9,"marketCap":null,"consecutiveDays":2,"totalChangePct":-2.56,"direction":"DOWN"},{"code":"CTSH","name":"CTSH","market":"US","currentPrice":43.63,"currentChangePct":-2.26,"yearLow":37.08,"yearHigh":87.03,"marketCap":null,"consecutiveDays":2,"totalChangePct":-2.55,"direction":"DOWN"},{"code":"REVB","name":"REVB","market":"US","currentPrice":1.15,"currentChangePct":-0.86,"yearLow":0.875,"yearHigh":12.72,"marketCap":null,"consecutiveDays":2,"totalChangePct":-2.54,"direction":"DOWN"},{"code":"YORW","name":"YORW","market":"US","currentPrice":30.66,"currentChangePct":-1.92,"yearLow":28.26,"yearHigh":34.3,"marketCap":null,"consecutiveDays":2,"totalChangePct":-2.51,"direction":"DOWN"},{"code":"HGTY","name":"HGTY","market":"US","currentPrice":11.72,"currentChangePct":-1.51,"yearLow":8.81,"yearHigh":14.0,"marketCap":null,"consecutiveDays":2,"totalChangePct":-2.5,"direction":"DOWN"},{"code":"AFRI","name":"AFRI","market":"US","currentPrice":10.58,"currentChangePct":-0.09,"yearLow":7.47,"yearHigh":11.42,"marketCap":null,"consecutiveDays":2,"totalChangePct":-2.49,"direction":"DOWN"},{"code":"MSEX","name":"MSEX","market":"US","currentPrice":56.01,"currentChangePct":-1.37,"yearLow":44.17,"yearHigh":62.18,"marketCap":null,"consecutiveDays":2,"totalChangePct":-2.49,"direction":"DOWN"},{"code":"IFF","name":"IFF","market":"US","currentPrice":76.26,"currentChangePct":-1.31,"yearLow":59.14,"yearHigh":84.45,"marketCap":null,"consecutiveDays":2,"totalChangePct":-2.48,"direction":"DOWN"},{"code":"BMR","name":"BMR","market":"US","currentPrice":1.2,"currentChangePct":-1.64,"yearLow":1.061,"yearHigh":3.85,"marketCap":null,"consecutiveDays":2,"totalChangePct":-2.44,"direction":"DOWN"},{"code":"SSTI","name":"SSTI","market":"US","currentPrice":8.38,"currentChangePct":-1.53,"yearLow":5.78,"yearHigh":13.34,"marketCap":null,"consecutiveDays":2,"totalChangePct":-2.44,"direction":"DOWN"},{"code":"CWT","name":"CWT","market":"US","currentPrice":50.62,"currentChangePct":-1.48,"yearLow":41.29,"yearHigh":52.51,"marketCap":null,"consecutiveDays":2,"totalChangePct":-2.43,"direction":"DOWN"},{"code":"STRR","name":"STRR","market":"US","currentPrice":10.89,"currentChangePct":-2.33,"yearLow":8.38,"yearHigh":11.99,"marketCap":null,"consecutiveDays":2,"totalChangePct":-2.42,"direction":"DOWN"},{"code":"PBHC","name":"PBHC","market":"US","currentPrice":15.995,"currentChangePct":-0.34,"yearLow":12.06,"yearHigh":17.4,"marketCap":null,"consecutiveDays":2,"totalChangePct":-2.41,"direction":"DOWN"},{"code":"SMHI","name":"SMHI","market":"US","currentPrice":7.72,"currentChangePct":-0.13,"yearLow":4.695,"yearHigh":8.51,"marketCap":null,"consecutiveDays":2,"totalChangePct":-2.4,"direction":"DOWN"},{"code":"GKOS","name":"GKOS","market":"US","currentPrice":153.09,"currentChangePct":-1.52,"yearLow":73.16,"yearHigh":161.53,"marketCap":null,"consecutiveDays":2,"totalChangePct":-2.38,"direction":"DOWN"},{"code":"ASTC","name":"ASTC","market":"US","currentPrice":7.55,"currentChangePct":-0.66,"yearLow":1.92,"yearHigh":68.85,"marketCap":null,"consecutiveDays":2,"totalChangePct":-2.33,"direction":"DOWN"},{"code":"GE","name":"GE","market":"US","currentPrice":340.7,"currentChangePct":-0.18,"yearLow":254.66,"yearHigh":382.97,"marketCap":null,"consecutiveDays":2,"totalChangePct":-2.33,"direction":"DOWN"},{"code":"NGG","name":"NGG","market":"US","currentPrice":82.05,"currentChangePct":-0.47,"yearLow":67.52,"yearHigh":94.64,"marketCap":null,"consecutiveDays":2,"totalChangePct":-2.31,"direction":"DOWN"},{"code":"SKYH","name":"SKYH","market":"US","currentPrice":10.18,"currentChangePct":-0.1,"yearLow":8.22,"yearHigh":11.171,"marketCap":null,"consecutiveDays":2,"totalChangePct":-2.3,"direction":"DOWN"},{"code":"RDN","name":"RDN","market":"US","currentPrice":38.48,"currentChangePct":-1.0,"yearLow":31.5,"yearHigh":41.05,"marketCap":null,"consecutiveDays":2,"totalChangePct":-2.29,"direction":"DOWN"},{"code":"MDWD","name":"MDWD","market":"US","currentPrice":14.28,"currentChangePct":-2.19,"yearLow":13.54,"yearHigh":21.11,"marketCap":null,"consecutiveDays":2,"totalChangePct":-2.26,"direction":"DOWN"},{"code":"ZETA","name":"ZETA","market":"US","currentPrice":21.19,"currentChangePct":-0.7,"yearLow":14.365,"yearHigh":25.95,"marketCap":null,"consecutiveDays":2,"totalChangePct":-2.26,"direction":"DOWN"},{"code":"EFOR","name":"EFOR","market":"US","currentPrice":18.31,"currentChangePct":-0.22,"yearLow":16.9,"yearHigh":60.75,"marketCap":null,"consecutiveDays":2,"totalChangePct":-2.24,"direction":"DOWN"},{"code":"SITC","name":"SITC","market":"US","currentPrice":4.38,"currentChangePct":-0.68,"yearLow":3.91,"yearHigh":12.39,"marketCap":null,"consecutiveDays":2,"totalChangePct":-2.23,"direction":"DOWN"},{"code":"SPKL","name":"SPKL","market":"US","currentPrice":11.85,"currentChangePct":-1.41,"yearLow":10.9,"yearHigh":13.93,"marketCap":null,"consecutiveDays":2,"totalChangePct":-2.23,"direction":"DOWN"},{"code":"ENB","name":"ENB","market":"US","currentPrice":55.46,"currentChangePct":-0.48,"yearLow":44.58,"yearHigh":58.45,"marketCap":null,"consecutiveDays":2,"totalChangePct":-2.2,"direction":"DOWN"},{"code":"FTNT","name":"FTNT","market":"US","currentPrice":158.1,"currentChangePct":-1.41,"yearLow":70.12,"yearHigh":170.35,"marketCap":null,"consecutiveDays":2,"totalChangePct":-2.17,"direction":"DOWN"},{"code":"GIGM","name":"GIGM","market":"US","currentPrice":1.36,"currentChangePct":-1.45,"yearLow":1.29,"yearHigh":1.89,"marketCap":null,"consecutiveDays":2,"totalChangePct":-2.16,"direction":"DOWN"},{"code":"HTO","name":"HTO","market":"US","currentPrice":64.02,"currentChangePct":-0.77,"yearLow":43.75,"yearHigh":66.05,"marketCap":null,"consecutiveDays":2,"totalChangePct":-2.15,"direction":"DOWN"},{"code":"ITRI","name":"ITRI","market":"US","currentPrice":84.14,"currentChangePct":-0.27,"yearLow":77.77,"yearHigh":142.0,"marketCap":null,"consecutiveDays":2,"totalChangePct":-2.15,"direction":"DOWN"},{"code":"WIT","name":"WIT","market":"US","currentPrice":1.82,"currentChangePct":-1.62,"yearLow":1.79,"yearHigh":3.09,"marketCap":null,"consecutiveDays":2,"totalChangePct":-2.15,"direction":"DOWN"},{"code":"GRWG","name":"GRWG","market":"US","currentPrice":1.4,"currentChangePct":-0.71,"yearLow":0.965,"yearHigh":2.4,"marketCap":null,"consecutiveDays":2,"totalChangePct":-2.1,"direction":"DOWN"},{"code":"CLST","name":"CLST","market":"US","currentPrice":16.92,"currentChangePct":-1.48,"yearLow":12.25,"yearHigh":18.16,"marketCap":null,"consecutiveDays":2,"totalChangePct":-2.08,"direction":"DOWN"},{"code":"GUG","name":"GUG","market":"US","currentPrice":16.03,"currentChangePct":-0.43,"yearLow":14.7,"yearHigh":16.46,"marketCap":null,"consecutiveDays":2,"totalChangePct":-2.08,"direction":"DOWN"},{"code":"FTS","name":"FTS","market":"US","currentPrice":57.57,"currentChangePct":-1.25,"yearLow":48.27,"yearHigh":59.08,"marketCap":null,"consecutiveDays":2,"totalChangePct":-2.06,"direction":"DOWN"},{"code":"SNY","name":"SNY","market":"US","currentPrice":43.75,"currentChangePct":-0.52,"yearLow":40.89,"yearHigh":52.68,"marketCap":null,"consecutiveDays":2,"totalChangePct":-2.04,"direction":"DOWN"},{"code":"WEX","name":"WEX","market":"US","currentPrice":160.96,"currentChangePct":-1.55,"yearLow":125.29,"yearHigh":186.86,"marketCap":null,"consecutiveDays":2,"totalChangePct":-2.03,"direction":"DOWN"},{"code":"HCSG","name":"HCSG","market":"US","currentPrice":24.8,"currentChangePct":-0.6,"yearLow":12.67,"yearHigh":25.75,"marketCap":null,"consecutiveDays":2,"totalChangePct":-2.02,"direction":"DOWN"},{"code":"ACU","name":"ACU","market":"US","currentPrice":46.62,"currentChangePct":-0.81,"yearLow":35.5,"yearHigh":50.0,"marketCap":null,"consecutiveDays":2,"totalChangePct":-1.96,"direction":"DOWN"},{"code":"ELLO","name":"ELLO","market":"US","currentPrice":18.53,"currentChangePct":-0.11,"yearLow":16.09,"yearHigh":30.34,"marketCap":null,"consecutiveDays":2,"totalChangePct":-1.96,"direction":"DOWN"},{"code":"MPV","name":"MPV","market":"US","currentPrice":15.5819,"currentChangePct":-1.57,"yearLow":15.568,"yearHigh":21.0,"marketCap":null,"consecutiveDays":2,"totalChangePct":-1.94,"direction":"DOWN"},{"code":"WTRG","name":"WTRG","market":"US","currentPrice":38.92,"currentChangePct":-1.19,"yearLow":36.11,"yearHigh":42.37,"marketCap":null,"consecutiveDays":2,"totalChangePct":-1.94,"direction":"DOWN"},{"code":"BHFAN","name":"BHFAN","market":"US","currentPrice":11.67,"currentChangePct":-1.64,"yearLow":11.511,"yearHigh":15.65,"marketCap":null,"consecutiveDays":2,"totalChangePct":-1.93,"direction":"DOWN"},{"code":"NET","name":"NET","market":"US","currentPrice":272.31,"currentChangePct":-0.04,"yearLow":158.83,"yearHigh":291.0,"marketCap":null,"consecutiveDays":2,"totalChangePct":-1.93,"direction":"DOWN"},{"code":"NTSK","name":"NTSK","market":"US","currentPrice":13.33,"currentChangePct":-1.41,"yearLow":7.665,"yearHigh":27.99,"marketCap":null,"consecutiveDays":2,"totalChangePct":-1.91,"direction":"DOWN"},{"code":"FAF","name":"FAF","market":"US","currentPrice":71.65,"currentChangePct":-0.11,"yearLow":56.2,"yearHigh":73.5,"marketCap":null,"consecutiveDays":2,"totalChangePct":-1.89,"direction":"DOWN"},{"code":"RCS","name":"RCS","market":"US","currentPrice":5.2,"currentChangePct":-0.19,"yearLow":5.09,"yearHigh":8.0,"marketCap":null,"consecutiveDays":2,"totalChangePct":-1.89,"direction":"DOWN"},{"code":"VMD","name":"VMD","market":"US","currentPrice":11.92,"currentChangePct":-0.42,"yearLow":5.93,"yearHigh":12.61,"marketCap":null,"consecutiveDays":2,"totalChangePct":-1.89,"direction":"DOWN"},{"code":"ZBRA","name":"ZBRA","market":"US","currentPrice":262.4,"currentChangePct":-0.87,"yearLow":199.05,"yearHigh":352.66,"marketCap":null,"consecutiveDays":2,"totalChangePct":-1.87,"direction":"DOWN"},{"code":"PTLE","name":"PTLE","market":"US","currentPrice":10.0,"currentChangePct":-0.2,"yearLow":4.0,"yearHigh":36.0,"marketCap":null,"consecutiveDays":2,"totalChangePct":-1.86,"direction":"DOWN"},{"code":"TKO","name":"TKO","market":"US","currentPrice":181.7,"currentChangePct":-0.6,"yearLow":152.29,"yearHigh":226.94,"marketCap":null,"consecutiveDays":2,"totalChangePct":-1.85,"direction":"DOWN"},{"code":"ESNT","name":"ESNT","market":"US","currentPrice":65.48,"currentChangePct":-1.04,"yearLow":55.34,"yearHigh":67.47,"marketCap":null,"consecutiveDays":2,"totalChangePct":-1.84,"direction":"DOWN"},{"code":"DGX","name":"DGX","market":"US","currentPrice":206.84,"currentChangePct":-0.39,"yearLow":165.78,"yearHigh":219.2,"marketCap":null,"consecutiveDays":2,"totalChangePct":-1.82,"direction":"DOWN"},{"code":"WLK","name":"WLK","market":"US","currentPrice":76.22,"currentChangePct":-0.9,"yearLow":56.33,"yearHigh":124.23,"marketCap":null,"consecutiveDays":2,"totalChangePct":-1.82,"direction":"DOWN"},{"code":"IMVT","name":"IMVT","market":"US","currentPrice":39.53,"currentChangePct":-0.98,"yearLow":14.32,"yearHigh":41.23,"marketCap":null,"consecutiveDays":2,"totalChangePct":-1.81,"direction":"DOWN"},{"code":"CDXS","name":"CDXS","market":"US","currentPrice":2.2,"currentChangePct":-0.45,"yearLow":0.96,"yearHigh":3.87,"marketCap":null,"consecutiveDays":2,"totalChangePct":-1.79,"direction":"DOWN"},{"code":"HUBB","name":"HUBB","market":"US","currentPrice":479.93,"currentChangePct":-1.04,"yearLow":403.82,"yearHigh":565.5,"marketCap":null,"consecutiveDays":2,"totalChangePct":-1.79,"direction":"DOWN"},{"code":"HURA","name":"HURA","market":"US","currentPrice":2.21,"currentChangePct":-1.34,"yearLow":0.41,"yearHigh":3.9,"marketCap":null,"consecutiveDays":2,"totalChangePct":-1.78,"direction":"DOWN"},{"code":"KR","name":"KR","market":"US","currentPrice":57.78,"currentChangePct":-0.99,"yearLow":54.15,"yearHigh":76.58,"marketCap":null,"consecutiveDays":2,"totalChangePct":-1.77,"direction":"DOWN"},{"code":"CGNX","name":"CGNX","market":"US","currentPrice":62.94,"currentChangePct":-0.22,"yearLow":33.45,"yearHigh":72.88,"marketCap":null,"consecutiveDays":2,"totalChangePct":-1.76,"direction":"DOWN"},{"code":"CLH","name":"CLH","market":"US","currentPrice":305.16,"currentChangePct":-1.63,"yearLow":201.34,"yearHigh":316.98,"marketCap":null,"consecutiveDays":2,"totalChangePct":-1.75,"direction":"DOWN"},{"code":"DRTS","name":"DRTS","market":"US","currentPrice":13.32,"currentChangePct":-1.11,"yearLow":2.87,"yearHigh":14.11,"marketCap":null,"consecutiveDays":2,"totalChangePct":-1.7,"direction":"DOWN"},{"code":"DXC","name":"DXC","market":"US","currentPrice":9.31,"currentChangePct":-0.21,"yearLow":7.9,"yearHigh":15.68,"marketCap":null,"consecutiveDays":2,"totalChangePct":-1.69,"direction":"DOWN"},{"code":"GGB","name":"GGB","market":"US","currentPrice":4.64,"currentChangePct":-0.85,"yearLow":2.85,"yearHigh":4.98,"marketCap":null,"consecutiveDays":2,"totalChangePct":-1.69,"direction":"DOWN"},{"code":"PBA","name":"PBA","market":"US","currentPrice":50.43,"currentChangePct":-0.55,"yearLow":35.45,"yearHigh":51.56,"marketCap":null,"consecutiveDays":2,"totalChangePct":-1.68,"direction":"DOWN"},{"code":"OMER","name":"OMER","market":"US","currentPrice":9.53,"currentChangePct":-1.04,"yearLow":3.44,"yearHigh":17.65,"marketCap":null,"consecutiveDays":2,"totalChangePct":-1.65,"direction":"DOWN"},{"code":"SPNT","name":"SPNT","market":"US","currentPrice":24.49,"currentChangePct":-0.69,"yearLow":17.17,"yearHigh":25.4,"marketCap":null,"consecutiveDays":2,"totalChangePct":-1.65,"direction":"DOWN"},{"code":"AFB","name":"AFB","market":"US","currentPrice":11.04,"currentChangePct":-1.52,"yearLow":10.08,"yearHigh":11.5,"marketCap":null,"consecutiveDays":2,"totalChangePct":-1.6,"direction":"DOWN"},{"code":"WPRT","name":"WPRT","market":"US","currentPrice":1.89,"currentChangePct":-0.53,"yearLow":1.54,"yearHigh":4.15,"marketCap":null,"consecutiveDays":2,"totalChangePct":-1.56,"direction":"DOWN"},{"code":"PMM","name":"PMM","market":"US","currentPrice":6.5,"currentChangePct":-0.76,"yearLow":5.77,"yearHigh":6.6,"marketCap":null,"consecutiveDays":2,"totalChangePct":-1.52,"direction":"DOWN"},{"code":"SIG","name":"SIG","market":"US","currentPrice":90.27,"currentChangePct":-0.19,"yearLow":71.62,"yearHigh":110.2,"marketCap":null,"consecutiveDays":2,"totalChangePct":-1.51,"direction":"DOWN"},{"code":"MCK","name":"MCK","market":"US","currentPrice":828.84,"currentChangePct":-0.32,"yearLow":637.0,"yearHigh":999.0,"marketCap":null,"consecutiveDays":2,"totalChangePct":-1.49,"direction":"DOWN"},{"code":"CALM","name":"CALM","market":"US","currentPrice":87.25,"currentChangePct":-1.32,"yearLow":71.92,"yearHigh":126.4,"marketCap":null,"consecutiveDays":2,"totalChangePct":-1.47,"direction":"DOWN"},{"code":"PML","name":"PML","market":"US","currentPrice":7.43,"currentChangePct":-1.2,"yearLow":7.1,"yearHigh":8.01,"marketCap":null,"consecutiveDays":2,"totalChangePct":-1.46,"direction":"DOWN"},{"code":"LSPD","name":"LSPD","market":"US","currentPrice":10.25,"currentChangePct":-1.16,"yearLow":7.83,"yearHigh":14.34,"marketCap":null,"consecutiveDays":2,"totalChangePct":-1.44,"direction":"DOWN"},{"code":"EG","name":"EG","market":"US","currentPrice":377.09,"currentChangePct":-0.5,"yearLow":302.44,"yearHigh":385.69,"marketCap":null,"consecutiveDays":2,"totalChangePct":-1.43,"direction":"DOWN"},{"code":"HDL","name":"HDL","market":"US","currentPrice":13.55,"currentChangePct":-0.75,"yearLow":12.0,"yearHigh":21.205,"marketCap":null,"consecutiveDays":2,"totalChangePct":-1.42,"direction":"DOWN"},{"code":"LH","name":"LH","market":"US","currentPrice":279.4,"currentChangePct":-0.74,"yearLow":244.52,"yearHigh":293.72,"marketCap":null,"consecutiveDays":2,"totalChangePct":-1.4,"direction":"DOWN"},{"code":"WHF","name":"WHF","market":"US","currentPrice":6.39,"currentChangePct":-0.93,"yearLow":6.07,"yearHigh":9.06,"marketCap":null,"consecutiveDays":2,"totalChangePct":-1.39,"direction":"DOWN"},{"code":"GEG","name":"GEG","market":"US","currentPrice":2.15,"currentChangePct":-0.46,"yearLow":1.8,"yearHigh":3.51,"marketCap":null,"consecutiveDays":2,"totalChangePct":-1.38,"direction":"DOWN"},{"code":"MMED","name":"MMED","market":"US","currentPrice":16.7,"currentChangePct":-1.3,"yearLow":10.65,"yearHigh":20.48,"marketCap":null,"consecutiveDays":2,"totalChangePct":-1.36,"direction":"DOWN"},{"code":"GRX","name":"GRX","market":"US","currentPrice":9.55,"currentChangePct":-0.1,"yearLow":8.8,"yearHigh":10.05,"marketCap":null,"consecutiveDays":2,"totalChangePct":-1.34,"direction":"DOWN"},{"code":"ZKH","name":"ZKH","market":"US","currentPrice":2.95,"currentChangePct":-0.34,"yearLow":1.92,"yearHigh":3.9,"marketCap":null,"consecutiveDays":2,"totalChangePct":-1.34,"direction":"DOWN"},{"code":"EHLD","name":"EHLD","market":"US","currentPrice":8.18,"currentChangePct":-1.21,"yearLow":6.11,"yearHigh":12.34,"marketCap":null,"consecutiveDays":2,"totalChangePct":-1.33,"direction":"DOWN"},{"code":"MOBI","name":"MOBI","market":"US","currentPrice":11.99,"currentChangePct":-0.17,"yearLow":10.19,"yearHigh":15.29,"marketCap":null,"consecutiveDays":2,"totalChangePct":-1.32,"direction":"DOWN"},{"code":"BGSI","name":"BGSI","market":"US","currentPrice":102.71,"currentChangePct":-0.64,"yearLow":88.97,"yearHigh":183.1,"marketCap":null,"consecutiveDays":2,"totalChangePct":-1.3,"direction":"DOWN"},{"code":"MNSBP","name":"MNSBP","market":"US","currentPrice":25.04,"currentChangePct":-0.48,"yearLow":23.22,"yearHigh":27.8,"marketCap":null,"consecutiveDays":2,"totalChangePct":-1.3,"direction":"DOWN"},{"code":"ARQQ","name":"ARQQ","market":"US","currentPrice":17.2,"currentChangePct":-0.06,"yearLow":11.52,"yearHigh":62.0,"marketCap":null,"consecutiveDays":2,"totalChangePct":-1.26,"direction":"DOWN"},{"code":"MTG","name":"MTG","market":"US","currentPrice":29.1,"currentChangePct":-0.75,"yearLow":24.69,"yearHigh":29.97,"marketCap":null,"consecutiveDays":2,"totalChangePct":-1.26,"direction":"DOWN"},{"code":"BHFAP","name":"BHFAP","market":"US","currentPrice":14.39,"currentChangePct":-1.03,"yearLow":14.02,"yearHigh":18.7,"marketCap":null,"consecutiveDays":2,"totalChangePct":-1.24,"direction":"DOWN"},{"code":"FTW","name":"FTW","market":"US","currentPrice":12.03,"currentChangePct":-0.41,"yearLow":9.5,"yearHigh":17.2,"marketCap":null,"consecutiveDays":2,"totalChangePct":-1.23,"direction":"DOWN"},{"code":"MLCIL","name":"MLCIL","market":"US","currentPrice":22.65,"currentChangePct":-0.66,"yearLow":21.97,"yearHigh":24.5,"marketCap":null,"consecutiveDays":2,"totalChangePct":-1.22,"direction":"DOWN"},{"code":"IHD","name":"IHD","market":"US","currentPrice":7.34,"currentChangePct":-0.68,"yearLow":5.75,"yearHigh":8.14,"marketCap":null,"consecutiveDays":2,"totalChangePct":-1.21,"direction":"DOWN"},{"code":"RGA","name":"RGA","market":"US","currentPrice":238.89,"currentChangePct":-0.83,"yearLow":165.52,"yearHigh":245.0,"marketCap":null,"consecutiveDays":2,"totalChangePct":-1.2,"direction":"DOWN"},{"code":"ATAI","name":"ATAI","market":"US","currentPrice":7.135,"currentChangePct":-0.76,"yearLow":3.06,"yearHigh":7.22,"marketCap":null,"consecutiveDays":2,"totalChangePct":-1.18,"direction":"DOWN"},{"code":"EVN","name":"EVN","market":"US","currentPrice":10.93,"currentChangePct":-1.09,"yearLow":10.09,"yearHigh":11.26,"marketCap":null,"consecutiveDays":2,"totalChangePct":-1.18,"direction":"DOWN"},{"code":"RCKT","name":"RCKT","market":"US","currentPrice":3.4,"currentChangePct":-0.87,"yearLow":2.53,"yearHigh":5.45,"marketCap":null,"consecutiveDays":2,"totalChangePct":-1.16,"direction":"DOWN"},{"code":"DOMO","name":"DOMO","market":"US","currentPrice":3.44,"currentChangePct":-0.58,"yearLow":1.84,"yearHigh":18.489,"marketCap":null,"consecutiveDays":2,"totalChangePct":-1.15,"direction":"DOWN"},{"code":"TACT","name":"TACT","market":"US","currentPrice":5.17,"currentChangePct":-0.19,"yearLow":3.06,"yearHigh":6.02,"marketCap":null,"consecutiveDays":2,"totalChangePct":-1.15,"direction":"DOWN"},{"code":"UTL","name":"UTL","market":"US","currentPrice":53.92,"currentChangePct":-0.74,"yearLow":44.61,"yearHigh":55.59,"marketCap":null,"consecutiveDays":2,"totalChangePct":-1.15,"direction":"DOWN"},{"code":"DMA","name":"DMA","market":"US","currentPrice":7.78,"currentChangePct":-0.77,"yearLow":6.94,"yearHigh":9.15,"marketCap":null,"consecutiveDays":2,"totalChangePct":-1.14,"direction":"DOWN"},{"code":"KRKR","name":"KRKR","market":"US","currentPrice":2.62,"currentChangePct":-0.0,"yearLow":2.5,"yearHigh":21.36,"marketCap":null,"consecutiveDays":2,"totalChangePct":-1.14,"direction":"DOWN"},{"code":"ENO","name":"ENO","market":"US","currentPrice":21.09,"currentChangePct":-0.75,"yearLow":21.0,"yearHigh":24.95,"marketCap":null,"consecutiveDays":2,"totalChangePct":-1.13,"direction":"DOWN"},{"code":"SRJN","name":"SRJN","market":"US","currentPrice":23.67,"currentChangePct":-0.75,"yearLow":23.51,"yearHigh":25.43,"marketCap":null,"consecutiveDays":2,"totalChangePct":-1.13,"direction":"DOWN"},{"code":"BHK","name":"BHK","market":"US","currentPrice":9.02,"currentChangePct":-0.44,"yearLow":8.69,"yearHigh":10.12,"marketCap":null,"consecutiveDays":2,"totalChangePct":-1.1,"direction":"DOWN"},{"code":"MXE","name":"MXE","market":"US","currentPrice":13.0,"currentChangePct":-0.91,"yearLow":10.21,"yearHigh":14.3,"marketCap":null,"consecutiveDays":2,"totalChangePct":-1.07,"direction":"DOWN"},{"code":"ADC","name":"ADC","market":"US","currentPrice":80.26,"currentChangePct":-0.38,"yearLow":69.56,"yearHigh":82.08,"marketCap":null,"consecutiveDays":2,"totalChangePct":-1.06,"direction":"DOWN"},{"code":"CNO","name":"CNO","market":"US","currentPrice":53.02,"currentChangePct":-0.02,"yearLow":35.24,"yearHigh":54.09,"marketCap":null,"consecutiveDays":2,"totalChangePct":-1.06,"direction":"DOWN"},{"code":"PHK","name":"PHK","market":"US","currentPrice":4.66,"currentChangePct":-0.21,"yearLow":4.41,"yearHigh":5.04,"marketCap":null,"consecutiveDays":2,"totalChangePct":-1.06,"direction":"DOWN"},{"code":"CAE","name":"CAE","market":"US","currentPrice":24.43,"currentChangePct":-0.57,"yearLow":22.76,"yearHigh":34.24,"marketCap":null,"consecutiveDays":2,"totalChangePct":-1.05,"direction":"DOWN"},{"code":"FMN","name":"FMN","market":"US","currentPrice":11.28,"currentChangePct":-0.88,"yearLow":10.4,"yearHigh":11.76,"marketCap":null,"consecutiveDays":2,"totalChangePct":-1.05,"direction":"DOWN"},{"code":"BFS","name":"BFS","market":"US","currentPrice":36.27,"currentChangePct":-0.11,"yearLow":29.16,"yearHigh":38.42,"marketCap":null,"consecutiveDays":2,"totalChangePct":-1.04,"direction":"DOWN"},{"code":"TXT","name":"TXT","market":"US","currentPrice":90.53,"currentChangePct":-0.29,"yearLow":75.8,"yearHigh":101.57,"marketCap":null,"consecutiveDays":2,"totalChangePct":-1.04,"direction":"DOWN"},{"code":"MT","name":"MT","market":"US","currentPrice":65.8,"currentChangePct":-0.08,"yearLow":30.17,"yearHigh":72.5,"marketCap":null,"consecutiveDays":2,"totalChangePct":-0.98,"direction":"DOWN"},{"code":"PECO","name":"PECO","market":"US","currentPrice":43.58,"currentChangePct":-0.43,"yearLow":32.84,"yearHigh":44.375,"marketCap":null,"consecutiveDays":2,"totalChangePct":-0.98,"direction":"DOWN"},{"code":"TRGP","name":"TRGP","market":"US","currentPrice":280.22,"currentChangePct":-0.75,"yearLow":144.14,"yearHigh":286.25,"marketCap":null,"consecutiveDays":2,"totalChangePct":-0.95,"direction":"DOWN"},{"code":"ITIC","name":"ITIC","market":"US","currentPrice":286.49,"currentChangePct":-0.22,"yearLow":200.95,"yearHigh":291.44,"marketCap":null,"consecutiveDays":2,"totalChangePct":-0.94,"direction":"DOWN"},{"code":"DHCNI","name":"DHCNI","market":"US","currentPrice":18.29,"currentChangePct":-0.44,"yearLow":15.61,"yearHigh":19.1,"marketCap":null,"consecutiveDays":2,"totalChangePct":-0.92,"direction":"DOWN"},{"code":"HESM","name":"HESM","market":"US","currentPrice":39.97,"currentChangePct":-0.57,"yearLow":31.63,"yearHigh":44.14,"marketCap":null,"consecutiveDays":2,"totalChangePct":-0.92,"direction":"DOWN"},{"code":"AFL","name":"AFL","market":"US","currentPrice":123.59,"currentChangePct":-0.39,"yearLow":96.95,"yearHigh":125.93,"marketCap":null,"consecutiveDays":2,"totalChangePct":-0.91,"direction":"DOWN"},{"code":"IIF","name":"IIF","market":"US","currentPrice":22.84,"currentChangePct":-0.31,"yearLow":19.83,"yearHigh":27.99,"marketCap":null,"consecutiveDays":2,"totalChangePct":-0.91,"direction":"DOWN"},{"code":"AXR","name":"AXR","market":"US","currentPrice":25.37,"currentChangePct":-0.51,"yearLow":17.61,"yearHigh":29.01,"marketCap":null,"consecutiveDays":2,"totalChangePct":-0.9,"direction":"DOWN"},{"code":"MFM","name":"MFM","market":"US","currentPrice":5.53,"currentChangePct":-0.54,"yearLow":5.03,"yearHigh":5.67,"marketCap":null,"consecutiveDays":2,"totalChangePct":-0.9,"direction":"DOWN"},{"code":"OXSQH","name":"OXSQH","market":"US","currentPrice":25.05,"currentChangePct":-0.2,"yearLow":24.61,"yearHigh":28.24,"marketCap":null,"consecutiveDays":2,"totalChangePct":-0.89,"direction":"DOWN"},{"code":"BIO","name":"BIO","market":"US","currentPrice":301.7,"currentChangePct":-0.07,"yearLow":236.73,"yearHigh":343.12,"marketCap":null,"consecutiveDays":2,"totalChangePct":-0.87,"direction":"DOWN"},{"code":"PFH","name":"PFH","market":"US","currentPrice":16.16,"currentChangePct":-0.62,"yearLow":16.08,"yearHigh":19.4,"marketCap":null,"consecutiveDays":2,"totalChangePct":-0.86,"direction":"DOWN"},{"code":"SPG","name":"SPG","market":"US","currentPrice":226.79,"currentChangePct":-0.61,"yearLow":159.7,"yearHigh":231.53,"marketCap":null,"consecutiveDays":2,"totalChangePct":-0.84,"direction":"DOWN"},{"code":"CCO","name":"CCO","market":"US","currentPrice":2.4,"currentChangePct":-0.41,"yearLow":1.0,"yearHigh":2.43,"marketCap":null,"consecutiveDays":2,"totalChangePct":-0.83,"direction":"DOWN"},{"code":"WTM","name":"WTM","market":"US","currentPrice":2193.26,"currentChangePct":-0.81,"yearLow":1648.0,"yearHigh":2333.0,"marketCap":null,"consecutiveDays":2,"totalChangePct":-0.83,"direction":"DOWN"},{"code":"POWWP","name":"POWWP","market":"US","currentPrice":24.09,"currentChangePct":-0.7,"yearLow":22.57,"yearHigh":25.495,"marketCap":null,"consecutiveDays":2,"totalChangePct":-0.82,"direction":"DOWN"},{"code":"TCBIO","name":"TCBIO","market":"US","currentPrice":20.57,"currentChangePct":-0.24,"yearLow":19.78,"yearHigh":22.945,"marketCap":null,"consecutiveDays":2,"totalChangePct":-0.82,"direction":"DOWN"},{"code":"ZS","name":"ZS","market":"US","currentPrice":148.72,"currentChangePct":-0.73,"yearLow":114.625,"yearHigh":336.99,"marketCap":null,"consecutiveDays":2,"totalChangePct":-0.81,"direction":"DOWN"},{"code":"KPET","name":"KPET","market":"US","currentPrice":9.97,"currentChangePct":-0.2,"yearLow":9.95,"yearHigh":10.15,"marketCap":null,"consecutiveDays":2,"totalChangePct":-0.8,"direction":"DOWN"},{"code":"BOW","name":"BOW","market":"US","currentPrice":30.46,"currentChangePct":-0.16,"yearLow":21.21,"yearHigh":33.86,"marketCap":null,"consecutiveDays":2,"totalChangePct":-0.78,"direction":"DOWN"},{"code":"DGICA","name":"DGICA","market":"US","currentPrice":18.57,"currentChangePct":-0.21,"yearLow":16.11,"yearHigh":21.06,"marketCap":null,"consecutiveDays":2,"totalChangePct":-0.75,"direction":"DOWN"},{"code":"ADAMM","name":"ADAMM","market":"US","currentPrice":25.033,"currentChangePct":-0.19,"yearLow":23.78,"yearHigh":25.62,"marketCap":null,"consecutiveDays":2,"totalChangePct":-0.74,"direction":"DOWN"},{"code":"INGR","name":"INGR","market":"US","currentPrice":101.8,"currentChangePct":-0.7,"yearLow":94.44,"yearHigh":135.68,"marketCap":null,"consecutiveDays":2,"totalChangePct":-0.74,"direction":"DOWN"},{"code":"PAI","name":"PAI","market":"US","currentPrice":12.0,"currentChangePct":-0.17,"yearLow":11.72,"yearHigh":13.09,"marketCap":null,"consecutiveDays":2,"totalChangePct":-0.74,"direction":"DOWN"},{"code":"RWTQ","name":"RWTQ","market":"US","currentPrice":24.34,"currentChangePct":-0.49,"yearLow":23.1,"yearHigh":26.3,"marketCap":null,"consecutiveDays":2,"totalChangePct":-0.73,"direction":"DOWN"},{"code":"DTB","name":"DTB","market":"US","currentPrice":16.5,"currentChangePct":-0.54,"yearLow":15.96,"yearHigh":19.178,"marketCap":null,"consecutiveDays":2,"totalChangePct":-0.72,"direction":"DOWN"},{"code":"REG","name":"REG","market":"US","currentPrice":82.09,"currentChangePct":-0.06,"yearLow":66.86,"yearHigh":83.66,"marketCap":null,"consecutiveDays":2,"totalChangePct":-0.71,"direction":"DOWN"},{"code":"VTEX","name":"VTEX","market":"US","currentPrice":4.17,"currentChangePct":-0.48,"yearLow":2.841,"yearHigh":6.34,"marketCap":null,"consecutiveDays":2,"totalChangePct":-0.71,"direction":"DOWN"},{"code":"AMX","name":"AMX","market":"US","currentPrice":26.09,"currentChangePct":-0.04,"yearLow":16.92,"yearHigh":28.46,"marketCap":null,"consecutiveDays":2,"totalChangePct":-0.69,"direction":"DOWN"},{"code":"FMY","name":"FMY","market":"US","currentPrice":11.61,"currentChangePct":-0.34,"yearLow":11.4,"yearHigh":12.39,"marketCap":null,"consecutiveDays":2,"totalChangePct":-0.68,"direction":"DOWN"},{"code":"TECH","name":"TECH","market":"US","currentPrice":71.63,"currentChangePct":-0.01,"yearLow":43.2,"yearHigh":72.16,"marketCap":null,"consecutiveDays":2,"totalChangePct":-0.68,"direction":"DOWN"},{"code":"KROS","name":"KROS","market":"US","currentPrice":10.57,"currentChangePct":-0.38,"yearLow":9.69,"yearHigh":22.55,"marketCap":null,"consecutiveDays":2,"totalChangePct":-0.66,"direction":"DOWN"},{"code":"ORI","name":"ORI","market":"US","currentPrice":41.96,"currentChangePct":-0.59,"yearLow":35.6,"yearHigh":46.76,"marketCap":null,"consecutiveDays":2,"totalChangePct":-0.66,"direction":"DOWN"},{"code":"NZF","name":"NZF","market":"US","currentPrice":12.4,"currentChangePct":-0.32,"yearLow":11.54,"yearHigh":13.02,"marketCap":null,"consecutiveDays":2,"totalChangePct":-0.64,"direction":"DOWN"},{"code":"HYFM","name":"HYFM","market":"US","currentPrice":0.678,"currentChangePct":-0.19,"yearLow":0.64,"yearHigh":4.78,"marketCap":null,"consecutiveDays":2,"totalChangePct":-0.63,"direction":"DOWN"},{"code":"IVT","name":"IVT","market":"US","currentPrice":36.5,"currentChangePct":-0.16,"yearLow":26.81,"yearHigh":37.22,"marketCap":null,"consecutiveDays":2,"totalChangePct":-0.63,"direction":"DOWN"},{"code":"TBLD","name":"TBLD","market":"US","currentPrice":21.91,"currentChangePct":-0.2,"yearLow":19.04,"yearHigh":23.02,"marketCap":null,"consecutiveDays":2,"totalChangePct":-0.63,"direction":"DOWN"},{"code":"ADAML","name":"ADAML","market":"US","currentPrice":24.35,"currentChangePct":-0.08,"yearLow":21.31,"yearHigh":24.55,"marketCap":null,"consecutiveDays":2,"totalChangePct":-0.61,"direction":"DOWN"},{"code":"H","name":"H","market":"US","currentPrice":189.51,"currentChangePct":-0.02,"yearLow":133.51,"yearHigh":206.86,"marketCap":null,"consecutiveDays":2,"totalChangePct":-0.6,"direction":"DOWN"},{"code":"RNR","name":"RNR","market":"US","currentPrice":321.18,"currentChangePct":-0.1,"yearLow":231.17,"yearHigh":329.57,"marketCap":null,"consecutiveDays":2,"totalChangePct":-0.58,"direction":"DOWN"},{"code":"HLXC","name":"HLXC","market":"US","currentPrice":10.52,"currentChangePct":-0.38,"yearLow":10.11,"yearHigh":11.0,"marketCap":null,"consecutiveDays":2,"totalChangePct":-0.57,"direction":"DOWN"},{"code":"ADAMG","name":"ADAMG","market":"US","currentPrice":24.98,"currentChangePct":-0.16,"yearLow":24.021,"yearHigh":25.47,"marketCap":null,"consecutiveDays":2,"totalChangePct":-0.56,"direction":"DOWN"},{"code":"BUI","name":"BUI","market":"US","currentPrice":27.72,"currentChangePct":-0.25,"yearLow":24.85,"yearHigh":30.8,"marketCap":null,"consecutiveDays":2,"totalChangePct":-0.54,"direction":"DOWN"},{"code":"PAY","name":"PAY","market":"US","currentPrice":29.62,"currentChangePct":-0.17,"yearLow":20.11,"yearHigh":39.38,"marketCap":null,"consecutiveDays":2,"totalChangePct":-0.54,"direction":"DOWN"},{"code":"QNCX","name":"QNCX","market":"US","currentPrice":18.78,"currentChangePct":-0.21,"yearLow":15.1,"yearHigh":910.0,"marketCap":null,"consecutiveDays":2,"totalChangePct":-0.53,"direction":"DOWN"},{"code":"VTN","name":"VTN","market":"US","currentPrice":11.31,"currentChangePct":-0.35,"yearLow":10.0,"yearHigh":12.1,"marketCap":null,"consecutiveDays":2,"totalChangePct":-0.53,"direction":"DOWN"},{"code":"SLMBP","name":"SLMBP","market":"US","currentPrice":74.25,"currentChangePct":-0.34,"yearLow":70.58,"yearHigh":83.05,"marketCap":null,"consecutiveDays":2,"totalChangePct":-0.52,"direction":"DOWN"},{"code":"WSBCO","name":"WSBCO","market":"US","currentPrice":25.6,"currentChangePct":-0.47,"yearLow":25.02,"yearHigh":26.03,"marketCap":null,"consecutiveDays":2,"totalChangePct":-0.51,"direction":"DOWN"},{"code":"RLTY","name":"RLTY","market":"US","currentPrice":15.98,"currentChangePct":-0.06,"yearLow":14.04,"yearHigh":16.11,"marketCap":null,"consecutiveDays":2,"totalChangePct":-0.5,"direction":"DOWN"},{"code":"BTZ","name":"BTZ","market":"US","currentPrice":10.16,"currentChangePct":-0.2,"yearLow":9.7,"yearHigh":11.18,"marketCap":null,"consecutiveDays":2,"totalChangePct":-0.49,"direction":"DOWN"},{"code":"TPGXL","name":"TPGXL","market":"US","currentPrice":23.09,"currentChangePct":-0.17,"yearLow":22.34,"yearHigh":26.25,"marketCap":null,"consecutiveDays":2,"totalChangePct":-0.47,"direction":"DOWN"},{"code":"MFAN","name":"MFAN","market":"US","currentPrice":25.38,"currentChangePct":-0.12,"yearLow":24.44,"yearHigh":25.75,"marketCap":null,"consecutiveDays":2,"totalChangePct":-0.43,"direction":"DOWN"},{"code":"BCCQU","name":"BCCQU","market":"US","currentPrice":10.06,"currentChangePct":-0.1,"yearLow":10.04,"yearHigh":10.1,"marketCap":null,"consecutiveDays":2,"totalChangePct":-0.4,"direction":"DOWN"},{"code":"BTT","name":"BTT","market":"US","currentPrice":22.54,"currentChangePct":-0.13,"yearLow":21.9,"yearHigh":23.24,"marketCap":null,"consecutiveDays":2,"totalChangePct":-0.4,"direction":"DOWN"},{"code":"CPBI","name":"CPBI","market":"US","currentPrice":20.12,"currentChangePct":-0.02,"yearLow":14.85,"yearHigh":21.835,"marketCap":null,"consecutiveDays":2,"totalChangePct":-0.4,"direction":"DOWN"},{"code":"CRBD","name":"CRBD","market":"US","currentPrice":22.55,"currentChangePct":-0.31,"yearLow":21.86,"yearHigh":25.34,"marketCap":null,"consecutiveDays":2,"totalChangePct":-0.4,"direction":"DOWN"},{"code":"CHSCO","name":"CHSCO","market":"US","currentPrice":25.78,"currentChangePct":-0.19,"yearLow":25.51,"yearHigh":27.16,"marketCap":null,"consecutiveDays":2,"totalChangePct":-0.39,"direction":"DOWN"},{"code":"ET","name":"ET","market":"US","currentPrice":20.25,"currentChangePct":-0.15,"yearLow":16.18,"yearHigh":20.7,"marketCap":null,"consecutiveDays":2,"totalChangePct":-0.34,"direction":"DOWN"},{"code":"RWTS","name":"RWTS","market":"US","currentPrice":24.815,"currentChangePct":-0.06,"yearLow":23.55,"yearHigh":24.99,"marketCap":null,"consecutiveDays":2,"totalChangePct":-0.34,"direction":"DOWN"},{"code":"MRSH","name":"MRSH","market":"US","currentPrice":181.59,"currentChangePct":-0.28,"yearLow":156.6,"yearHigh":213.8,"marketCap":null,"consecutiveDays":2,"totalChangePct":-0.32,"direction":"DOWN"},{"code":"NTRSO","name":"NTRSO","market":"US","currentPrice":18.57,"currentChangePct":-0.27,"yearLow":18.235,"yearHigh":21.149,"marketCap":null,"consecutiveDays":2,"totalChangePct":-0.32,"direction":"DOWN"},{"code":"CIMP","name":"CIMP","market":"US","currentPrice":25.45,"currentChangePct":-0.16,"yearLow":24.25,"yearHigh":25.64,"marketCap":null,"consecutiveDays":2,"totalChangePct":-0.31,"direction":"DOWN"},{"code":"FOX","name":"FOX","market":"US","currentPrice":51.47,"currentChangePct":-0.16,"yearLow":44.08,"yearHigh":68.175,"marketCap":null,"consecutiveDays":2,"totalChangePct":-0.31,"direction":"DOWN"},{"code":"HACQ","name":"HACQ","market":"US","currentPrice":10.06,"currentChangePct":-0.2,"yearLow":9.86,"yearHigh":10.09,"marketCap":null,"consecutiveDays":2,"totalChangePct":-0.3,"direction":"DOWN"},{"code":"AIIA","name":"AIIA","market":"US","currentPrice":10.16,"currentChangePct":-0.1,"yearLow":9.85,"yearHigh":10.25,"marketCap":null,"consecutiveDays":2,"totalChangePct":-0.29,"direction":"DOWN"},{"code":"CEPV","name":"CEPV","market":"US","currentPrice":10.42,"currentChangePct":-0.19,"yearLow":10.06,"yearHigh":10.48,"marketCap":null,"consecutiveDays":2,"totalChangePct":-0.29,"direction":"DOWN"},{"code":"SAAQ","name":"SAAQ","market":"US","currentPrice":10.17,"currentChangePct":-0.2,"yearLow":9.88,"yearHigh":11.1,"marketCap":null,"consecutiveDays":2,"totalChangePct":-0.29,"direction":"DOWN"},{"code":"TACO","name":"TACO","market":"US","currentPrice":10.47,"currentChangePct":-0.19,"yearLow":10.11,"yearHigh":10.69,"marketCap":null,"consecutiveDays":2,"totalChangePct":-0.29,"direction":"DOWN"},{"code":"WTFCN","name":"WTFCN","market":"US","currentPrice":26.06,"currentChangePct":-0.15,"yearLow":25.5,"yearHigh":27.31,"marketCap":null,"consecutiveDays":2,"totalChangePct":-0.27,"direction":"DOWN"},{"code":"ACA","name":"ACA","market":"US","currentPrice":144.65,"currentChangePct":-0.06,"yearLow":81.91,"yearHigh":146.92,"marketCap":null,"consecutiveDays":2,"totalChangePct":-0.25,"direction":"DOWN"},{"code":"ATLCZ","name":"ATLCZ","market":"US","currentPrice":25.31,"currentChangePct":-0.16,"yearLow":24.72,"yearHigh":25.89,"marketCap":null,"consecutiveDays":2,"totalChangePct":-0.24,"direction":"DOWN"},{"code":"BCSS","name":"BCSS","market":"US","currentPrice":10.195,"currentChangePct":-0.15,"yearLow":9.95,"yearHigh":10.29,"marketCap":null,"consecutiveDays":2,"totalChangePct":-0.24,"direction":"DOWN"},{"code":"GIW","name":"GIW","market":"US","currentPrice":10.08,"currentChangePct":-0.05,"yearLow":9.87,"yearHigh":10.115,"marketCap":null,"consecutiveDays":2,"totalChangePct":-0.2,"direction":"DOWN"},{"code":"IRHO","name":"IRHO","market":"US","currentPrice":10.01,"currentChangePct":-0.1,"yearLow":9.85,"yearHigh":10.14,"marketCap":null,"consecutiveDays":2,"totalChangePct":-0.2,"direction":"DOWN"},{"code":"PTOR","name":"PTOR","market":"US","currentPrice":9.98,"currentChangePct":-0.1,"yearLow":9.77,"yearHigh":10.04,"marketCap":null,"consecutiveDays":2,"totalChangePct":-0.2,"direction":"DOWN"},{"code":"RWTP","name":"RWTP","market":"US","currentPrice":24.5,"currentChangePct":-0.15,"yearLow":22.95,"yearHigh":25.89,"marketCap":null,"consecutiveDays":2,"totalChangePct":-0.2,"direction":"DOWN"},{"code":"HOVNP","name":"HOVNP","market":"US","currentPrice":20.541,"currentChangePct":-0.04,"yearLow":17.15,"yearHigh":21.9,"marketCap":null,"consecutiveDays":2,"totalChangePct":-0.19,"direction":"DOWN"},{"code":"CTGG","name":"CTGG","market":"US","currentPrice":17.36,"currentChangePct":-0.06,"yearLow":16.63,"yearHigh":19.2,"marketCap":null,"consecutiveDays":2,"totalChangePct":-0.17,"direction":"DOWN"},{"code":"ADAMI","name":"ADAMI","market":"US","currentPrice":25.16,"currentChangePct":-0.14,"yearLow":24.07,"yearHigh":25.58,"marketCap":null,"consecutiveDays":2,"totalChangePct":-0.16,"direction":"DOWN"},{"code":"CCCTU","name":"CCCTU","market":"US","currentPrice":10.015,"currentChangePct":-0.05,"yearLow":10.0,"yearHigh":10.08,"marketCap":null,"consecutiveDays":2,"totalChangePct":-0.15,"direction":"DOWN"},{"code":"NSTS","name":"NSTS","market":"US","currentPrice":13.79,"currentChangePct":-0.07,"yearLow":10.72,"yearHigh":13.84,"marketCap":null,"consecutiveDays":2,"totalChangePct":-0.14,"direction":"DOWN"},{"code":"AGNCN","name":"AGNCN","market":"US","currentPrice":25.61,"currentChangePct":-0.04,"yearLow":24.65,"yearHigh":26.11,"marketCap":null,"consecutiveDays":2,"totalChangePct":-0.12,"direction":"DOWN"}]}