{"meta":{"country":"US","date":"2026-07-08","updatedAt":"2026-07-08 19:46:33 KST","status":"COMPLETED","totalTickers":6782,"detectedCombos":121,"source":"yahoo"},"results":[{"code":"CRNX","name":"CRNX","market":"US","currentPrice":83.53,"currentChangePct":98.74,"yearLow":25.83,"yearHigh":83.631,"consecutiveDays":6,"totalChangePct":138.73,"direction":"UP"},{"code":"RNAZ","name":"RNAZ","market":"US","currentPrice":8.44,"currentChangePct":8.62,"yearLow":3.82,"yearHigh":20.99,"consecutiveDays":6,"totalChangePct":85.49,"direction":"UP"},{"code":"XHLD","name":"XHLD","market":"US","currentPrice":2.13,"currentChangePct":13.3,"yearLow":1.03,"yearHigh":13.47,"consecutiveDays":6,"totalChangePct":76.03,"direction":"UP"},{"code":"SKIN","name":"SKIN","market":"US","currentPrice":1.11,"currentChangePct":47.02,"yearLow":0.551,"yearHigh":2.69,"consecutiveDays":6,"totalChangePct":73.44,"direction":"UP"},{"code":"ICU","name":"ICU","market":"US","currentPrice":5.07,"currentChangePct":6.51,"yearLow":2.07,"yearHigh":12.5,"consecutiveDays":6,"totalChangePct":70.13,"direction":"UP"},{"code":"ALIT","name":"ALIT","market":"US","currentPrice":19.04,"currentChangePct":13.94,"yearLow":9.58,"yearHigh":121.8,"consecutiveDays":6,"totalChangePct":68.79,"direction":"UP"},{"code":"AKTX","name":"AKTX","market":"US","currentPrice":15.48,"currentChangePct":42.02,"yearLow":3.015,"yearHigh":49.6,"consecutiveDays":6,"totalChangePct":62.61,"direction":"UP"},{"code":"FATE","name":"FATE","market":"US","currentPrice":3.02,"currentChangePct":1.0,"yearLow":0.91,"yearHigh":3.21,"consecutiveDays":6,"totalChangePct":61.5,"direction":"UP"},{"code":"OXBR","name":"OXBR","market":"US","currentPrice":1.47,"currentChangePct":0.68,"yearLow":0.66,"yearHigh":2.86,"consecutiveDays":6,"totalChangePct":56.38,"direction":"UP"},{"code":"RTB","name":"RTB","market":"US","currentPrice":16.83,"currentChangePct":0.06,"yearLow":3.25,"yearHigh":26.25,"consecutiveDays":6,"totalChangePct":51.21,"direction":"UP"},{"code":"FHTX","name":"FHTX","market":"US","currentPrice":6.0,"currentChangePct":18.81,"yearLow":3.27,"yearHigh":6.95,"consecutiveDays":6,"totalChangePct":48.88,"direction":"UP"},{"code":"SNWV","name":"SNWV","market":"US","currentPrice":10.82,"currentChangePct":3.05,"yearLow":7.53,"yearHigh":46.585,"consecutiveDays":6,"totalChangePct":41.81,"direction":"UP"},{"code":"NIQ","name":"NIQ","market":"US","currentPrice":11.0,"currentChangePct":12.02,"yearLow":7.93,"yearHigh":20.39,"consecutiveDays":6,"totalChangePct":38.02,"direction":"UP"},{"code":"NABL","name":"NABL","market":"US","currentPrice":4.38,"currentChangePct":3.79,"yearLow":2.92,"yearHigh":9.04,"consecutiveDays":6,"totalChangePct":37.3,"direction":"UP"},{"code":"EDIT","name":"EDIT","market":"US","currentPrice":3.75,"currentChangePct":2.74,"yearLow":1.66,"yearHigh":4.537,"consecutiveDays":6,"totalChangePct":36.86,"direction":"UP"},{"code":"PEW","name":"PEW","market":"US","currentPrice":3.12,"currentChangePct":9.47,"yearLow":2.245,"yearHigh":21.4,"consecutiveDays":6,"totalChangePct":36.24,"direction":"UP"},{"code":"BNR","name":"BNR","market":"US","currentPrice":10.745,"currentChangePct":4.02,"yearLow":3.51,"yearHigh":41.72,"consecutiveDays":6,"totalChangePct":35.16,"direction":"UP"},{"code":"TENX","name":"TENX","market":"US","currentPrice":17.38,"currentChangePct":6.89,"yearLow":5.684,"yearHigh":18.38,"consecutiveDays":6,"totalChangePct":34.83,"direction":"UP"},{"code":"PLRZ","name":"PLRZ","market":"US","currentPrice":15.25,"currentChangePct":0.28,"yearLow":2.88,"yearHigh":18.2,"consecutiveDays":6,"totalChangePct":33.54,"direction":"UP"},{"code":"FORR","name":"FORR","market":"US","currentPrice":9.66,"currentChangePct":0.31,"yearLow":4.88,"yearHigh":11.57,"consecutiveDays":6,"totalChangePct":33.43,"direction":"UP"},{"code":"AEYE","name":"AEYE","market":"US","currentPrice":7.41,"currentChangePct":2.35,"yearLow":5.31,"yearHigh":16.39,"consecutiveDays":6,"totalChangePct":32.56,"direction":"UP"},{"code":"ADCT","name":"ADCT","market":"US","currentPrice":1.35,"currentChangePct":8.0,"yearLow":0.78,"yearHigh":4.98,"consecutiveDays":6,"totalChangePct":32.35,"direction":"UP"},{"code":"KELYB","name":"KELYB","market":"US","currentPrice":23.61,"currentChangePct":2.7,"yearLow":8.38,"yearHigh":125.0,"consecutiveDays":6,"totalChangePct":31.17,"direction":"UP"},{"code":"AKBA","name":"AKBA","market":"US","currentPrice":1.36,"currentChangePct":4.62,"yearLow":0.823,"yearHigh":4.079,"consecutiveDays":6,"totalChangePct":30.77,"direction":"UP"},{"code":"REAX","name":"REAX","market":"US","currentPrice":2.25,"currentChangePct":2.27,"yearLow":1.55,"yearHigh":5.405,"consecutiveDays":6,"totalChangePct":30.06,"direction":"UP"},{"code":"DCGO","name":"DCGO","market":"US","currentPrice":0.5955,"currentChangePct":1.36,"yearLow":0.451,"yearHigh":1.78,"consecutiveDays":6,"totalChangePct":29.57,"direction":"UP"},{"code":"MRKR","name":"MRKR","market":"US","currentPrice":1.68,"currentChangePct":13.51,"yearLow":0.81,"yearHigh":4.07,"consecutiveDays":6,"totalChangePct":28.24,"direction":"UP"},{"code":"INTA","name":"INTA","market":"US","currentPrice":28.18,"currentChangePct":2.1,"yearLow":19.01,"yearHigh":48.43,"consecutiveDays":6,"totalChangePct":27.97,"direction":"UP"},{"code":"LB","name":"LB","market":"US","currentPrice":77.44,"currentChangePct":3.39,"yearLow":43.75,"yearHigh":85.6,"consecutiveDays":6,"totalChangePct":27.14,"direction":"UP"},{"code":"SANA","name":"SANA","market":"US","currentPrice":4.12,"currentChangePct":3.78,"yearLow":2.61,"yearHigh":6.55,"consecutiveDays":6,"totalChangePct":26.38,"direction":"UP"},{"code":"NAVN","name":"NAVN","market":"US","currentPrice":27.25,"currentChangePct":3.61,"yearLow":8.105,"yearHigh":28.22,"consecutiveDays":6,"totalChangePct":26.22,"direction":"UP"},{"code":"ZNTL","name":"ZNTL","market":"US","currentPrice":4.78,"currentChangePct":1.27,"yearLow":1.185,"yearHigh":6.95,"consecutiveDays":6,"totalChangePct":26.12,"direction":"UP"},{"code":"TTAN","name":"TTAN","market":"US","currentPrice":79.7,"currentChangePct":2.46,"yearLow":54.17,"yearHigh":119.99,"consecutiveDays":6,"totalChangePct":25.71,"direction":"UP"},{"code":"MNDY","name":"MNDY","market":"US","currentPrice":84.1,"currentChangePct":1.94,"yearLow":57.5,"yearHigh":314.995,"consecutiveDays":6,"totalChangePct":25.35,"direction":"UP"},{"code":"CSTE","name":"CSTE","market":"US","currentPrice":2.41,"currentChangePct":2.55,"yearLow":0.56,"yearHigh":2.62,"consecutiveDays":6,"totalChangePct":24.87,"direction":"UP"},{"code":"ACOG","name":"ACOG","market":"US","currentPrice":8.1,"currentChangePct":2.53,"yearLow":4.5,"yearHigh":11.54,"consecutiveDays":6,"totalChangePct":24.62,"direction":"UP"},{"code":"NOW","name":"NOW","market":"US","currentPrice":110.73,"currentChangePct":2.59,"yearLow":81.24,"yearHigh":210.2,"consecutiveDays":6,"totalChangePct":23.69,"direction":"UP"},{"code":"FDS","name":"FDS","market":"US","currentPrice":258.3,"currentChangePct":2.42,"yearLow":185.0,"yearHigh":453.41,"consecutiveDays":6,"totalChangePct":23.68,"direction":"UP"},{"code":"VERX","name":"VERX","market":"US","currentPrice":13.4,"currentChangePct":4.28,"yearLow":10.21,"yearHigh":36.75,"consecutiveDays":6,"totalChangePct":23.62,"direction":"UP"},{"code":"YEXT","name":"YEXT","market":"US","currentPrice":5.13,"currentChangePct":2.81,"yearLow":3.265,"yearHigh":9.2,"consecutiveDays":6,"totalChangePct":23.61,"direction":"UP"},{"code":"SRPT","name":"SRPT","market":"US","currentPrice":19.79,"currentChangePct":3.18,"yearLow":10.42,"yearHigh":25.32,"consecutiveDays":6,"totalChangePct":23.53,"direction":"UP"},{"code":"HSDT","name":"HSDT","market":"US","currentPrice":1.84,"currentChangePct":1.1,"yearLow":1.185,"yearHigh":25.5,"consecutiveDays":6,"totalChangePct":23.49,"direction":"UP"},{"code":"DXC","name":"DXC","market":"US","currentPrice":10.16,"currentChangePct":1.2,"yearLow":7.9,"yearHigh":16.42,"consecutiveDays":6,"totalChangePct":23.45,"direction":"UP"},{"code":"NP","name":"NP","market":"US","currentPrice":33.79,"currentChangePct":1.2,"yearLow":14.78,"yearHigh":34.61,"consecutiveDays":6,"totalChangePct":23.14,"direction":"UP"},{"code":"STTK","name":"STTK","market":"US","currentPrice":7.26,"currentChangePct":0.28,"yearLow":0.712,"yearHigh":8.33,"consecutiveDays":6,"totalChangePct":22.84,"direction":"UP"},{"code":"QTWO","name":"QTWO","market":"US","currentPrice":53.95,"currentChangePct":1.01,"yearLow":40.79,"yearHigh":95.1,"consecutiveDays":6,"totalChangePct":22.5,"direction":"UP"},{"code":"BRBR","name":"BRBR","market":"US","currentPrice":13.94,"currentChangePct":3.64,"yearLow":7.82,"yearHigh":59.095,"consecutiveDays":6,"totalChangePct":22.39,"direction":"UP"},{"code":"BILL","name":"BILL","market":"US","currentPrice":40.68,"currentChangePct":1.12,"yearLow":31.41,"yearHigh":57.21,"consecutiveDays":6,"totalChangePct":21.87,"direction":"UP"},{"code":"CBZ","name":"CBZ","market":"US","currentPrice":37.0,"currentChangePct":4.64,"yearLow":24.29,"yearHigh":77.91,"consecutiveDays":6,"totalChangePct":21.71,"direction":"UP"},{"code":"VEEV","name":"VEEV","market":"US","currentPrice":192.3,"currentChangePct":0.15,"yearLow":148.05,"yearHigh":310.5,"consecutiveDays":6,"totalChangePct":21.65,"direction":"UP"},{"code":"NKTX","name":"NKTX","market":"US","currentPrice":3.38,"currentChangePct":2.42,"yearLow":1.69,"yearHigh":3.65,"consecutiveDays":6,"totalChangePct":21.58,"direction":"UP"},{"code":"RMAX","name":"RMAX","market":"US","currentPrice":11.55,"currentChangePct":1.85,"yearLow":5.46,"yearHigh":11.81,"consecutiveDays":6,"totalChangePct":21.58,"direction":"UP"},{"code":"S","name":"S","market":"US","currentPrice":18.16,"currentChangePct":0.06,"yearLow":11.81,"yearHigh":21.4,"consecutiveDays":6,"totalChangePct":21.39,"direction":"UP"},{"code":"SDA","name":"SDA","market":"US","currentPrice":0.91,"currentChangePct":1.11,"yearLow":0.47,"yearHigh":2.93,"consecutiveDays":6,"totalChangePct":21.01,"direction":"UP"},{"code":"CNDT","name":"CNDT","market":"US","currentPrice":1.57,"currentChangePct":2.61,"yearLow":1.15,"yearHigh":2.98,"consecutiveDays":6,"totalChangePct":20.77,"direction":"UP"},{"code":"NKTR","name":"NKTR","market":"US","currentPrice":74.9,"currentChangePct":2.39,"yearLow":21.02,"yearHigh":109.0,"consecutiveDays":6,"totalChangePct":20.75,"direction":"UP"},{"code":"WIX","name":"WIX","market":"US","currentPrice":50.36,"currentChangePct":0.3,"yearLow":40.16,"yearHigh":190.93,"consecutiveDays":6,"totalChangePct":20.71,"direction":"UP"},{"code":"CELC","name":"CELC","market":"US","currentPrice":115.72,"currentChangePct":6.58,"yearLow":13.31,"yearHigh":151.02,"consecutiveDays":6,"totalChangePct":20.63,"direction":"UP"},{"code":"APPN","name":"APPN","market":"US","currentPrice":24.68,"currentChangePct":1.23,"yearLow":18.63,"yearHigh":46.059,"consecutiveDays":6,"totalChangePct":19.63,"direction":"UP"},{"code":"ASMB","name":"ASMB","market":"US","currentPrice":28.965,"currentChangePct":0.24,"yearLow":16.9,"yearHigh":39.71,"consecutiveDays":6,"totalChangePct":19.41,"direction":"UP"},{"code":"KRRO","name":"KRRO","market":"US","currentPrice":14.49,"currentChangePct":3.06,"yearLow":5.204,"yearHigh":55.89,"consecutiveDays":6,"totalChangePct":19.06,"direction":"UP"},{"code":"KINS","name":"KINS","market":"US","currentPrice":20.27,"currentChangePct":0.7,"yearLow":13.08,"yearHigh":20.79,"consecutiveDays":6,"totalChangePct":18.89,"direction":"UP"},{"code":"DSS","name":"DSS","market":"US","currentPrice":0.64,"currentChangePct":2.56,"yearLow":0.361,"yearHigh":1.895,"consecutiveDays":6,"totalChangePct":18.52,"direction":"UP"},{"code":"YYAI","name":"YYAI","market":"US","currentPrice":7.58,"currentChangePct":0.13,"yearLow":6.4,"yearHigh":10576.0,"consecutiveDays":6,"totalChangePct":18.44,"direction":"UP"},{"code":"VANI","name":"VANI","market":"US","currentPrice":1.35,"currentChangePct":3.85,"yearLow":0.923,"yearHigh":1.92,"consecutiveDays":6,"totalChangePct":18.42,"direction":"UP"},{"code":"TEAM","name":"TEAM","market":"US","currentPrice":88.39,"currentChangePct":3.38,"yearLow":56.01,"yearHigh":222.59,"consecutiveDays":6,"totalChangePct":18.36,"direction":"UP"},{"code":"KYTX","name":"KYTX","market":"US","currentPrice":9.68,"currentChangePct":5.68,"yearLow":2.52,"yearHigh":13.67,"consecutiveDays":6,"totalChangePct":18.05,"direction":"UP"},{"code":"BAER","name":"BAER","market":"US","currentPrice":1.95,"currentChangePct":1.56,"yearLow":1.47,"yearHigh":3.44,"consecutiveDays":6,"totalChangePct":17.47,"direction":"UP"},{"code":"ABUS","name":"ABUS","market":"US","currentPrice":5.18,"currentChangePct":4.23,"yearLow":3.08,"yearHigh":5.34,"consecutiveDays":6,"totalChangePct":17.46,"direction":"UP"},{"code":"SNDX","name":"SNDX","market":"US","currentPrice":23.24,"currentChangePct":5.25,"yearLow":8.71,"yearHigh":25.59,"consecutiveDays":6,"totalChangePct":17.31,"direction":"UP"},{"code":"INTS","name":"INTS","market":"US","currentPrice":4.78,"currentChangePct":5.75,"yearLow":3.51,"yearHigh":43.5,"consecutiveDays":6,"totalChangePct":17.16,"direction":"UP"},{"code":"REKR","name":"REKR","market":"US","currentPrice":0.7097,"currentChangePct":2.01,"yearLow":0.602,"yearHigh":3.42,"consecutiveDays":6,"totalChangePct":16.97,"direction":"UP"},{"code":"TDC","name":"TDC","market":"US","currentPrice":36.46,"currentChangePct":0.05,"yearLow":19.83,"yearHigh":41.78,"consecutiveDays":6,"totalChangePct":16.97,"direction":"UP"},{"code":"HBNB","name":"HBNB","market":"US","currentPrice":5.87,"currentChangePct":7.12,"yearLow":1.55,"yearHigh":10.43,"consecutiveDays":6,"totalChangePct":16.93,"direction":"UP"},{"code":"AJG","name":"AJG","market":"US","currentPrice":254.67,"currentChangePct":1.96,"yearLow":190.75,"yearHigh":316.89,"consecutiveDays":6,"totalChangePct":16.9,"direction":"UP"},{"code":"CYPH","name":"CYPH","market":"US","currentPrice":0.7,"currentChangePct":3.7,"yearLow":0.232,"yearHigh":3.7,"consecutiveDays":6,"totalChangePct":16.86,"direction":"UP"},{"code":"CMRC","name":"CMRC","market":"US","currentPrice":3.19,"currentChangePct":0.31,"yearLow":2.41,"yearHigh":5.545,"consecutiveDays":6,"totalChangePct":16.85,"direction":"UP"},{"code":"NRXP","name":"NRXP","market":"US","currentPrice":4.16,"currentChangePct":5.45,"yearLow":1.62,"yearHigh":5.055,"consecutiveDays":6,"totalChangePct":16.85,"direction":"UP"},{"code":"IMTE","name":"IMTE","market":"US","currentPrice":0.537,"currentChangePct":3.67,"yearLow":0.4,"yearHigh":1.54,"consecutiveDays":6,"totalChangePct":16.74,"direction":"UP"},{"code":"RMNI","name":"RMNI","market":"US","currentPrice":4.75,"currentChangePct":1.93,"yearLow":2.87,"yearHigh":5.38,"consecutiveDays":6,"totalChangePct":16.71,"direction":"UP"},{"code":"LOT","name":"LOT","market":"US","currentPrice":1.26,"currentChangePct":0.8,"yearLow":1.0,"yearHigh":2.5,"consecutiveDays":6,"totalChangePct":16.67,"direction":"UP"},{"code":"NAMS","name":"NAMS","market":"US","currentPrice":36.99,"currentChangePct":5.99,"yearLow":19.28,"yearHigh":42.205,"consecutiveDays":6,"totalChangePct":16.58,"direction":"UP"},{"code":"DKNG","name":"DKNG","market":"US","currentPrice":26.91,"currentChangePct":2.67,"yearLow":20.46,"yearHigh":48.78,"consecutiveDays":6,"totalChangePct":16.49,"direction":"UP"},{"code":"TOMZ","name":"TOMZ","market":"US","currentPrice":0.85,"currentChangePct":1.19,"yearLow":0.5,"yearHigh":1.2,"consecutiveDays":6,"totalChangePct":16.44,"direction":"UP"},{"code":"AHG","name":"AHG","market":"US","currentPrice":1.56,"currentChangePct":2.3,"yearLow":1.07,"yearHigh":2.5,"consecutiveDays":6,"totalChangePct":16.42,"direction":"UP"},{"code":"HQY","name":"HQY","market":"US","currentPrice":96.98,"currentChangePct":0.42,"yearLow":72.76,"yearHigh":105.96,"consecutiveDays":6,"totalChangePct":16.24,"direction":"UP"},{"code":"PRPO","name":"PRPO","market":"US","currentPrice":26.0,"currentChangePct":2.93,"yearLow":13.02,"yearHigh":33.63,"consecutiveDays":6,"totalChangePct":16.05,"direction":"UP"},{"code":"BOX","name":"BOX","market":"US","currentPrice":28.85,"currentChangePct":1.76,"yearLow":21.34,"yearHigh":33.88,"consecutiveDays":6,"totalChangePct":15.72,"direction":"UP"},{"code":"PRGO","name":"PRGO","market":"US","currentPrice":11.19,"currentChangePct":0.9,"yearLow":9.23,"yearHigh":28.44,"consecutiveDays":6,"totalChangePct":15.6,"direction":"UP"},{"code":"PASG","name":"PASG","market":"US","currentPrice":5.0,"currentChangePct":6.38,"yearLow":3.29,"yearHigh":20.0,"consecutiveDays":6,"totalChangePct":15.47,"direction":"UP"},{"code":"ALRM","name":"ALRM","market":"US","currentPrice":50.84,"currentChangePct":1.95,"yearLow":41.49,"yearHigh":59.53,"consecutiveDays":6,"totalChangePct":15.36,"direction":"UP"},{"code":"PINS","name":"PINS","market":"US","currentPrice":22.42,"currentChangePct":0.76,"yearLow":13.84,"yearHigh":39.93,"consecutiveDays":6,"totalChangePct":15.09,"direction":"UP"},{"code":"WEX","name":"WEX","market":"US","currentPrice":153.14,"currentChangePct":2.32,"yearLow":125.29,"yearHigh":186.86,"consecutiveDays":6,"totalChangePct":15.07,"direction":"UP"},{"code":"DBX","name":"DBX","market":"US","currentPrice":28.85,"currentChangePct":1.19,"yearLow":21.695,"yearHigh":32.4,"consecutiveDays":6,"totalChangePct":15.03,"direction":"UP"},{"code":"EFX","name":"EFX","market":"US","currentPrice":174.58,"currentChangePct":1.54,"yearLow":150.75,"yearHigh":275.91,"consecutiveDays":6,"totalChangePct":14.91,"direction":"UP"},{"code":"CRMD","name":"CRMD","market":"US","currentPrice":8.87,"currentChangePct":0.91,"yearLow":6.13,"yearHigh":14.96,"consecutiveDays":6,"totalChangePct":14.9,"direction":"UP"},{"code":"TOST","name":"TOST","market":"US","currentPrice":29.61,"currentChangePct":0.44,"yearLow":22.26,"yearHigh":49.66,"consecutiveDays":6,"totalChangePct":14.9,"direction":"UP"},{"code":"KD","name":"KD","market":"US","currentPrice":12.39,"currentChangePct":0.9,"yearLow":10.1,"yearHigh":44.2,"consecutiveDays":6,"totalChangePct":14.83,"direction":"UP"},{"code":"CLMB","name":"CLMB","market":"US","currentPrice":25.42,"currentChangePct":5.0,"yearLow":15.25,"yearHigh":36.255,"consecutiveDays":6,"totalChangePct":14.81,"direction":"UP"},{"code":"FSLY","name":"FSLY","market":"US","currentPrice":18.59,"currentChangePct":1.86,"yearLow":6.29,"yearHigh":34.82,"consecutiveDays":6,"totalChangePct":14.65,"direction":"UP"},{"code":"NTNX","name":"NTNX","market":"US","currentPrice":53.76,"currentChangePct":2.56,"yearLow":34.01,"yearHigh":82.42,"consecutiveDays":6,"totalChangePct":14.53,"direction":"UP"},{"code":"BFAM","name":"BFAM","market":"US","currentPrice":76.62,"currentChangePct":1.2,"yearLow":57.63,"yearHigh":130.76,"consecutiveDays":6,"totalChangePct":14.51,"direction":"UP"},{"code":"LPLA","name":"LPLA","market":"US","currentPrice":307.58,"currentChangePct":0.93,"yearLow":260.15,"yearHigh":403.58,"consecutiveDays":6,"totalChangePct":14.45,"direction":"UP"},{"code":"TYL","name":"TYL","market":"US","currentPrice":321.45,"currentChangePct":0.76,"yearLow":270.71,"yearHigh":621.34,"consecutiveDays":6,"totalChangePct":14.36,"direction":"UP"},{"code":"SCHW","name":"SCHW","market":"US","currentPrice":101.93,"currentChangePct":1.3,"yearLow":83.96,"yearHigh":107.5,"consecutiveDays":6,"totalChangePct":13.96,"direction":"UP"},{"code":"USNA","name":"USNA","market":"US","currentPrice":22.38,"currentChangePct":2.75,"yearLow":16.6,"yearHigh":38.32,"consecutiveDays":6,"totalChangePct":13.72,"direction":"UP"},{"code":"BWIN","name":"BWIN","market":"US","currentPrice":27.3,"currentChangePct":0.78,"yearLow":15.88,"yearHigh":43.64,"consecutiveDays":6,"totalChangePct":13.7,"direction":"UP"},{"code":"GRAB","name":"GRAB","market":"US","currentPrice":3.93,"currentChangePct":2.08,"yearLow":3.18,"yearHigh":6.62,"consecutiveDays":6,"totalChangePct":13.58,"direction":"UP"},{"code":"JXG","name":"JXG","market":"US","currentPrice":11.35,"currentChangePct":0.18,"yearLow":3.01,"yearHigh":24.15,"consecutiveDays":6,"totalChangePct":13.5,"direction":"UP"},{"code":"YSG","name":"YSG","market":"US","currentPrice":3.54,"currentChangePct":0.28,"yearLow":2.15,"yearHigh":11.04,"consecutiveDays":6,"totalChangePct":13.46,"direction":"UP"},{"code":"META","name":"META","market":"US","currentPrice":615.58,"currentChangePct":2.55,"yearLow":520.26,"yearHigh":796.25,"consecutiveDays":6,"totalChangePct":13.39,"direction":"UP"},{"code":"GLIBK","name":"GLIBK","market":"US","currentPrice":22.49,"currentChangePct":0.4,"yearLow":19.3,"yearHigh":41.175,"consecutiveDays":6,"totalChangePct":13.24,"direction":"UP"},{"code":"BOW","name":"BOW","market":"US","currentPrice":32.0,"currentChangePct":1.49,"yearLow":21.21,"yearHigh":35.35,"consecutiveDays":6,"totalChangePct":13.23,"direction":"UP"},{"code":"RDCM","name":"RDCM","market":"US","currentPrice":14.24,"currentChangePct":0.56,"yearLow":10.41,"yearHigh":16.74,"consecutiveDays":6,"totalChangePct":13.2,"direction":"UP"},{"code":"FIS","name":"FIS","market":"US","currentPrice":42.6,"currentChangePct":3.22,"yearLow":37.42,"yearHigh":82.62,"consecutiveDays":6,"totalChangePct":12.52,"direction":"UP"},{"code":"AVIR","name":"AVIR","market":"US","currentPrice":4.88,"currentChangePct":0.21,"yearLow":2.78,"yearHigh":6.45,"consecutiveDays":6,"totalChangePct":12.18,"direction":"UP"},{"code":"NRDS","name":"NRDS","market":"US","currentPrice":9.5,"currentChangePct":0.21,"yearLow":7.33,"yearHigh":16.24,"consecutiveDays":6,"totalChangePct":11.63,"direction":"UP"},{"code":"UHS","name":"UHS","market":"US","currentPrice":161.26,"currentChangePct":2.03,"yearLow":140.08,"yearHigh":246.33,"consecutiveDays":6,"totalChangePct":11.63,"direction":"UP"},{"code":"AMSF","name":"AMSF","market":"US","currentPrice":35.45,"currentChangePct":2.31,"yearLow":29.42,"yearHigh":47.86,"consecutiveDays":6,"totalChangePct":11.37,"direction":"UP"},{"code":"HBIO","name":"HBIO","market":"US","currentPrice":6.63,"currentChangePct":4.41,"yearLow":3.8,"yearHigh":9.4,"consecutiveDays":6,"totalChangePct":11.24,"direction":"UP"},{"code":"U","name":"U","market":"US","currentPrice":29.66,"currentChangePct":0.03,"yearLow":16.78,"yearHigh":52.15,"consecutiveDays":6,"totalChangePct":11.04,"direction":"UP"},{"code":"EHC","name":"EHC","market":"US","currentPrice":110.72,"currentChangePct":3.49,"yearLow":92.77,"yearHigh":127.99,"consecutiveDays":6,"totalChangePct":11.03,"direction":"UP"},{"code":"WVE","name":"WVE","market":"US","currentPrice":6.38,"currentChangePct":0.95,"yearLow":5.02,"yearHigh":21.73,"consecutiveDays":6,"totalChangePct":10.96,"direction":"UP"},{"code":"ESTC","name":"ESTC","market":"US","currentPrice":59.46,"currentChangePct":1.57,"yearLow":42.05,"yearHigh":96.07,"consecutiveDays":6,"totalChangePct":10.93,"direction":"UP"},{"code":"NRC","name":"NRC","market":"US","currentPrice":22.77,"currentChangePct":1.2,"yearLow":11.014,"yearHigh":23.0,"consecutiveDays":6,"totalChangePct":10.86,"direction":"UP"},{"code":"SONY","name":"SONY","market":"US","currentPrice":21.4,"currentChangePct":1.13,"yearLow":19.32,"yearHigh":30.34,"consecutiveDays":6,"totalChangePct":10.77,"direction":"UP"},{"code":"NVAX","name":"NVAX","market":"US","currentPrice":9.46,"currentChangePct":1.18,"yearLow":6.2,"yearHigh":11.97,"consecutiveDays":6,"totalChangePct":10.51,"direction":"UP"},{"code":"EXLS","name":"EXLS","market":"US","currentPrice":27.84,"currentChangePct":2.62,"yearLow":24.85,"yearHigh":47.11,"consecutiveDays":6,"totalChangePct":10.39,"direction":"UP"},{"code":"ALNY","name":"ALNY","market":"US","currentPrice":321.59,"currentChangePct":2.73,"yearLow":273.11,"yearHigh":495.55,"consecutiveDays":6,"totalChangePct":10.37,"direction":"UP"},{"code":"CNA","name":"CNA","market":"US","currentPrice":51.8,"currentChangePct":0.23,"yearLow":41.53,"yearHigh":52.86,"consecutiveDays":6,"totalChangePct":10.35,"direction":"UP"},{"code":"URGN","name":"URGN","market":"US","currentPrice":37.75,"currentChangePct":0.91,"yearLow":13.26,"yearHigh":39.585,"consecutiveDays":6,"totalChangePct":9.8,"direction":"UP"},{"code":"IGIC","name":"IGIC","market":"US","currentPrice":28.25,"currentChangePct":1.25,"yearLow":20.82,"yearHigh":28.62,"consecutiveDays":6,"totalChangePct":9.75,"direction":"UP"},{"code":"DDL","name":"DDL","market":"US","currentPrice":2.04,"currentChangePct":0.99,"yearLow":1.65,"yearHigh":3.41,"consecutiveDays":6,"totalChangePct":9.68,"direction":"UP"},{"code":"LYFT","name":"LYFT","market":"US","currentPrice":15.44,"currentChangePct":0.32,"yearLow":12.46,"yearHigh":25.54,"consecutiveDays":6,"totalChangePct":9.66,"direction":"UP"},{"code":"CPAY","name":"CPAY","market":"US","currentPrice":357.1,"currentChangePct":0.15,"yearLow":252.84,"yearHigh":367.43,"consecutiveDays":6,"totalChangePct":9.6,"direction":"UP"},{"code":"JAZZ","name":"JAZZ","market":"US","currentPrice":247.72,"currentChangePct":1.45,"yearLow":105.0,"yearHigh":249.64,"consecutiveDays":6,"totalChangePct":9.51,"direction":"UP"},{"code":"HCA","name":"HCA","market":"US","currentPrice":423.11,"currentChangePct":1.45,"yearLow":330.0,"yearHigh":556.52,"consecutiveDays":6,"totalChangePct":9.35,"direction":"UP"},{"code":"BR","name":"BR","market":"US","currentPrice":148.6,"currentChangePct":2.65,"yearLow":133.83,"yearHigh":271.91,"consecutiveDays":6,"totalChangePct":9.06,"direction":"UP"},{"code":"NMM","name":"NMM","market":"US","currentPrice":75.18,"currentChangePct":0.44,"yearLow":37.42,"yearHigh":80.69,"consecutiveDays":6,"totalChangePct":9.0,"direction":"UP"},{"code":"EG","name":"EG","market":"US","currentPrice":373.22,"currentChangePct":0.08,"yearLow":302.44,"yearHigh":379.22,"consecutiveDays":6,"totalChangePct":8.8,"direction":"UP"},{"code":"CCEC","name":"CCEC","market":"US","currentPrice":22.32,"currentChangePct":1.55,"yearLow":16.77,"yearHigh":24.83,"consecutiveDays":6,"totalChangePct":8.4,"direction":"UP"},{"code":"TAK","name":"TAK","market":"US","currentPrice":16.96,"currentChangePct":0.41,"yearLow":12.99,"yearHigh":18.9,"consecutiveDays":6,"totalChangePct":8.37,"direction":"UP"},{"code":"AMZN","name":"AMZN","market":"US","currentPrice":245.98,"currentChangePct":0.75,"yearLow":196.0,"yearHigh":278.56,"consecutiveDays":6,"totalChangePct":8.36,"direction":"UP"},{"code":"TOUR","name":"TOUR","market":"US","currentPrice":4.94,"currentChangePct":1.44,"yearLow":4.53,"yearHigh":9.85,"consecutiveDays":6,"totalChangePct":8.33,"direction":"UP"},{"code":"PRI","name":"PRI","market":"US","currentPrice":302.55,"currentChangePct":1.13,"yearLow":230.09,"yearHigh":305.14,"consecutiveDays":6,"totalChangePct":7.53,"direction":"UP"},{"code":"AIZ","name":"AIZ","market":"US","currentPrice":280.11,"currentChangePct":0.3,"yearLow":183.39,"yearHigh":284.12,"consecutiveDays":6,"totalChangePct":7.42,"direction":"UP"},{"code":"MTN","name":"MTN","market":"US","currentPrice":143.16,"currentChangePct":0.73,"yearLow":118.51,"yearHigh":172.0,"consecutiveDays":6,"totalChangePct":7.36,"direction":"UP"},{"code":"SMPL","name":"SMPL","market":"US","currentPrice":13.17,"currentChangePct":1.62,"yearLow":10.21,"yearHigh":34.19,"consecutiveDays":6,"totalChangePct":7.16,"direction":"UP"},{"code":"PFG","name":"PFG","market":"US","currentPrice":112.88,"currentChangePct":0.29,"yearLow":75.0,"yearHigh":113.86,"consecutiveDays":6,"totalChangePct":7.06,"direction":"UP"},{"code":"GRMN","name":"GRMN","market":"US","currentPrice":248.68,"currentChangePct":1.41,"yearLow":186.67,"yearHigh":273.32,"consecutiveDays":6,"totalChangePct":6.95,"direction":"UP"},{"code":"TARA","name":"TARA","market":"US","currentPrice":4.27,"currentChangePct":4.66,"yearLow":2.81,"yearHigh":7.82,"consecutiveDays":6,"totalChangePct":6.75,"direction":"UP"},{"code":"DGICA","name":"DGICA","market":"US","currentPrice":19.24,"currentChangePct":0.89,"yearLow":16.11,"yearHigh":21.06,"consecutiveDays":6,"totalChangePct":6.59,"direction":"UP"},{"code":"ZTO","name":"ZTO","market":"US","currentPrice":23.17,"currentChangePct":0.61,"yearLow":17.39,"yearHigh":26.2,"consecutiveDays":6,"totalChangePct":6.28,"direction":"UP"},{"code":"FOCL","name":"FOCL","market":"US","currentPrice":5.35,"currentChangePct":1.52,"yearLow":1.21,"yearHigh":5.42,"consecutiveDays":6,"totalChangePct":5.94,"direction":"UP"},{"code":"LOAN","name":"LOAN","market":"US","currentPrice":4.69,"currentChangePct":3.3,"yearLow":4.13,"yearHigh":5.8,"consecutiveDays":6,"totalChangePct":5.87,"direction":"UP"},{"code":"SAH","name":"SAH","market":"US","currentPrice":87.26,"currentChangePct":1.57,"yearLow":54.11,"yearHigh":89.62,"consecutiveDays":6,"totalChangePct":5.5,"direction":"UP"},{"code":"BHST","name":"BHST","market":"US","currentPrice":2.9,"currentChangePct":0.35,"yearLow":2.745,"yearHigh":12.8,"consecutiveDays":6,"totalChangePct":5.45,"direction":"UP"},{"code":"NATR","name":"NATR","market":"US","currentPrice":21.75,"currentChangePct":0.37,"yearLow":12.97,"yearHigh":28.14,"consecutiveDays":6,"totalChangePct":5.22,"direction":"UP"},{"code":"AFG","name":"AFG","market":"US","currentPrice":142.8,"currentChangePct":0.54,"yearLow":122.11,"yearHigh":150.02,"consecutiveDays":6,"totalChangePct":5.08,"direction":"UP"},{"code":"IMKTA","name":"IMKTA","market":"US","currentPrice":92.14,"currentChangePct":1.79,"yearLow":59.27,"yearHigh":95.62,"consecutiveDays":6,"totalChangePct":4.37,"direction":"UP"},{"code":"ETJ","name":"ETJ","market":"US","currentPrice":8.43,"currentChangePct":0.36,"yearLow":7.88,"yearHigh":9.12,"consecutiveDays":6,"totalChangePct":4.33,"direction":"UP"},{"code":"TR","name":"TR","market":"US","currentPrice":38.45,"currentChangePct":0.13,"yearLow":32.689,"yearHigh":45.06,"consecutiveDays":6,"totalChangePct":4.31,"direction":"UP"},{"code":"ADX","name":"ADX","market":"US","currentPrice":25.81,"currentChangePct":0.43,"yearLow":20.91,"yearHigh":25.84,"consecutiveDays":6,"totalChangePct":4.24,"direction":"UP"},{"code":"BHF","name":"BHF","market":"US","currentPrice":65.27,"currentChangePct":0.6,"yearLow":42.07,"yearHigh":66.33,"consecutiveDays":6,"totalChangePct":4.07,"direction":"UP"},{"code":"ALCO","name":"ALCO","market":"US","currentPrice":42.03,"currentChangePct":0.48,"yearLow":31.32,"yearHigh":45.01,"consecutiveDays":6,"totalChangePct":4.06,"direction":"UP"},{"code":"XYF","name":"XYF","market":"US","currentPrice":4.97,"currentChangePct":0.2,"yearLow":3.3,"yearHigh":20.36,"consecutiveDays":6,"totalChangePct":3.97,"direction":"UP"},{"code":"SMC","name":"SMC","market":"US","currentPrice":30.21,"currentChangePct":0.2,"yearLow":19.13,"yearHigh":33.5,"consecutiveDays":6,"totalChangePct":3.92,"direction":"UP"},{"code":"HTOO","name":"HTOO","market":"US","currentPrice":2.69,"currentChangePct":0.37,"yearLow":2.41,"yearHigh":12.63,"consecutiveDays":6,"totalChangePct":3.86,"direction":"UP"},{"code":"CICB","name":"CICB","market":"US","currentPrice":25.57,"currentChangePct":2.73,"yearLow":24.41,"yearHigh":26.0,"consecutiveDays":6,"totalChangePct":3.73,"direction":"UP"},{"code":"BRW","name":"BRW","market":"US","currentPrice":6.76,"currentChangePct":0.6,"yearLow":6.38,"yearHigh":8.49,"consecutiveDays":6,"totalChangePct":3.21,"direction":"UP"},{"code":"FUND","name":"FUND","market":"US","currentPrice":9.63,"currentChangePct":1.05,"yearLow":7.5,"yearHigh":10.47,"consecutiveDays":6,"totalChangePct":2.45,"direction":"UP"},{"code":"BANX","name":"BANX","market":"US","currentPrice":19.84,"currentChangePct":0.56,"yearLow":18.45,"yearHigh":23.67,"consecutiveDays":6,"totalChangePct":2.22,"direction":"UP"},{"code":"BUSEP","name":"BUSEP","market":"US","currentPrice":25.92,"currentChangePct":0.04,"yearLow":25.0,"yearHigh":26.65,"consecutiveDays":6,"totalChangePct":1.89,"direction":"UP"},{"code":"CIMP","name":"CIMP","market":"US","currentPrice":25.44,"currentChangePct":0.67,"yearLow":24.25,"yearHigh":25.64,"consecutiveDays":6,"totalChangePct":1.35,"direction":"UP"},{"code":"BHFAN","name":"BHFAN","market":"US","currentPrice":12.13,"currentChangePct":0.12,"yearLow":11.511,"yearHigh":15.65,"consecutiveDays":6,"totalChangePct":1.25,"direction":"UP"},{"code":"MGRB","name":"MGRB","market":"US","currentPrice":16.41,"currentChangePct":0.06,"yearLow":15.81,"yearHigh":19.099,"consecutiveDays":6,"totalChangePct":0.92,"direction":"UP"},{"code":"APGE","name":"APGE","market":"US","currentPrice":133.54,"currentChangePct":0.03,"yearLow":34.34,"yearHigh":133.87,"consecutiveDays":6,"totalChangePct":0.75,"direction":"UP"},{"code":"RILYN","name":"RILYN","market":"US","currentPrice":24.99,"currentChangePct":0.04,"yearLow":14.42,"yearHigh":25.05,"consecutiveDays":6,"totalChangePct":0.4,"direction":"UP"},{"code":"KMPB","name":"KMPB","market":"US","currentPrice":23.96,"currentChangePct":0.38,"yearLow":22.03,"yearHigh":24.28,"consecutiveDays":6,"totalChangePct":0.38,"direction":"UP"}]}